{"contacts": [{"terms": [{"accession": "MS:1000586", "name": "contact name", "value": "Vinothini Rajeeve"}, {"accession": "MS:1000589", "name": "contact email", "value": "v.rajeeve@qmul.ac.uk"}, {"accession": "MS:1000590", "name": "contact affiliation", "value": "Centre for Haemato Oncology"}, {"accession": "MS:1002037", "name": "dataset submitter"}]}, {"terms": [{"accession": "MS:1002332", "name": "lab head"}, {"accession": "MS:1000586", "name": "contact name", "value": "Dr Pedro Cutillas"}, {"accession": "MS:1000589", "name": "contact email", "value": "p.cutillas@qmul.ac.uk"}, {"accession": "MS:1000590", "name": "contact affiliation", "value": "Cell Signalling & Proteomics Group, Barts Cancer Institute, Queen Mary University of London, London, UK"}]}], "datasetFiles": [{"accession": "MS:1002849", "name": "Search engine output file URI", "value": "ftp://ftp.pride.ebi.ac.uk/pride/data/archive/2019/11/PXD013003/F001291.mzid"}, {"accession": "MS:1002849", "name": "Search engine output file URI", "value": "ftp://ftp.pride.ebi.ac.uk/pride/data/archive/2019/11/PXD013003/F001296.mzid"}, {"accession": "MS:1002849", "name": "Search engine output file URI", "value": "ftp://ftp.pride.ebi.ac.uk/pride/data/archive/2019/11/PXD013003/F001298.mzid"}, {"accession": "MS:1002849", "name": "Search engine output file URI", "value": "ftp://ftp.pride.ebi.ac.uk/pride/data/archive/2019/11/PXD013003/F001301.mzid"}, {"accession": "MS:1002849", "name": "Search engine output file URI", "value": "ftp://ftp.pride.ebi.ac.uk/pride/data/archive/2019/11/PXD013003/F001303.mzid"}, {"accession": "MS:1002849", "name": "Search engine output file URI", "value": "ftp://ftp.pride.ebi.ac.uk/pride/data/archive/2019/11/PXD013003/F001305.mzid"}, {"accession": "MS:1002849", "name": "Search engine output file URI", "value": "ftp://ftp.pride.ebi.ac.uk/pride/data/archive/2019/11/PXD013003/F001308.mzid"}, {"accession": "MS:1002849", "name": "Search engine output file URI", "value": "ftp://ftp.pride.ebi.ac.uk/pride/data/archive/2019/11/PXD013003/F001310.mzid"}, {"accession": "MS:1002849", "name": "Search engine output file URI", "value": "ftp://ftp.pride.ebi.ac.uk/pride/data/archive/2019/11/PXD013003/F001312.mzid"}, {"accession": "MS:1002849", "name": "Search engine output file URI", "value": "ftp://ftp.pride.ebi.ac.uk/pride/data/archive/2019/11/PXD013003/F001315.mzid"}, {"accession": "MS:1002849", "name": "Search engine output file URI", "value": "ftp://ftp.pride.ebi.ac.uk/pride/data/archive/2019/11/PXD013003/F001317.mzid"}, {"accession": "MS:1002849", "name": "Search engine output file URI", "value": "ftp://ftp.pride.ebi.ac.uk/pride/data/archive/2019/11/PXD013003/F001319.mzid"}, {"accession": "MS:1002849", "name": "Search engine output file URI", "value": "ftp://ftp.pride.ebi.ac.uk/pride/data/archive/2019/11/PXD013003/F001322.mzid"}, {"accession": "MS:1002849", "name": "Search engine output file URI", "value": "ftp://ftp.pride.ebi.ac.uk/pride/data/archive/2019/11/PXD013003/F001324.mzid"}, {"accession": "MS:1002849", "name": "Search engine output file URI", "value": "ftp://ftp.pride.ebi.ac.uk/pride/data/archive/2019/11/PXD013003/F001327.mzid"}, {"accession": "MS:1002849", "name": "Search engine output file URI", "value": "ftp://ftp.pride.ebi.ac.uk/pride/data/archive/2019/11/PXD013003/F001328.mzid"}, {"accession": "MS:1002849", "name": "Search engine output file URI", "value": "ftp://ftp.pride.ebi.ac.uk/pride/data/archive/2019/11/PXD013003/F002337.mzid"}, {"accession": "MS:1002849", "name": "Search engine output file URI", "value": "ftp://ftp.pride.ebi.ac.uk/pride/data/archive/2019/11/PXD013003/F002338.mzid"}, {"accession": "MS:1002849", "name": "Search engine output file URI", "value": "ftp://ftp.pride.ebi.ac.uk/pride/data/archive/2019/11/PXD013003/F002339.mzid"}, {"accession": "MS:1002849", "name": "Search engine output file URI", "value": "ftp://ftp.pride.ebi.ac.uk/pride/data/archive/2019/11/PXD013003/F002340.mzid"}, {"accession": "MS:1002849", "name": "Search engine output file URI", "value": "ftp://ftp.pride.ebi.ac.uk/pride/data/archive/2019/11/PXD013003/F002341.mzid"}, {"accession": "MS:1002849", "name": "Search engine output file URI", "value": "ftp://ftp.pride.ebi.ac.uk/pride/data/archive/2019/11/PXD013003/F002342.mzid"}, {"accession": "MS:1002849", "name": "Search engine output file URI", "value": "ftp://ftp.pride.ebi.ac.uk/pride/data/archive/2019/11/PXD013003/F002343.mzid"}, {"accession": "MS:1002849", "name": "Search engine output file URI", "value": "ftp://ftp.pride.ebi.ac.uk/pride/data/archive/2019/11/PXD013003/F002344.mzid"}, {"accession": "MS:1002849", "name": "Search engine output file URI", "value": "ftp://ftp.pride.ebi.ac.uk/pride/data/archive/2019/11/PXD013003/F002345.mzid"}, {"accession": "MS:1002849", "name": "Search engine output file URI", "value": "ftp://ftp.pride.ebi.ac.uk/pride/data/archive/2019/11/PXD013003/F002346.mzid"}, {"accession": "MS:1002849", "name": "Search engine output file URI", "value": "ftp://ftp.pride.ebi.ac.uk/pride/data/archive/2019/11/PXD013003/F002347.mzid"}, {"accession": "MS:1002849", "name": "Search engine output file URI", "value": "ftp://ftp.pride.ebi.ac.uk/pride/data/archive/2019/11/PXD013003/F002348.mzid"}, {"accession": "MS:1002849", "name": "Search engine output file URI", "value": "ftp://ftp.pride.ebi.ac.uk/pride/data/archive/2019/11/PXD013003/F002349.mzid"}, {"accession": "MS:1002849", "name": "Search engine output file URI", "value": "ftp://ftp.pride.ebi.ac.uk/pride/data/archive/2019/11/PXD013003/F002350.mzid"}, {"accession": "MS:1002849", "name": "Search engine output file URI", "value": "ftp://ftp.pride.ebi.ac.uk/pride/data/archive/2019/11/PXD013003/F002351.mzid"}, {"accession": "MS:1002849", "name": "Search engine output file URI", "value": "ftp://ftp.pride.ebi.ac.uk/pride/data/archive/2019/11/PXD013003/F002352.mzid"}, {"accession": "MS:1002849", "name": "Search engine output file URI", "value": "ftp://ftp.pride.ebi.ac.uk/pride/data/archive/2019/11/PXD013003/F004898.mzid"}, {"accession": "MS:1002849", "name": "Search engine output file URI", "value": "ftp://ftp.pride.ebi.ac.uk/pride/data/archive/2019/11/PXD013003/F004899.mzid"}, {"accession": "MS:1002849", "name": "Search engine output file URI", "value": "ftp://ftp.pride.ebi.ac.uk/pride/data/archive/2019/11/PXD013003/F004900.mzid"}, {"accession": "MS:1002849", "name": "Search engine output file URI", "value": "ftp://ftp.pride.ebi.ac.uk/pride/data/archive/2019/11/PXD013003/F004902.mzid"}, {"accession": "MS:1002849", "name": "Search engine output file URI", "value": "ftp://ftp.pride.ebi.ac.uk/pride/data/archive/2019/11/PXD013003/F004903.mzid"}, {"accession": "MS:1002849", "name": "Search engine output file URI", "value": "ftp://ftp.pride.ebi.ac.uk/pride/data/archive/2019/11/PXD013003/F004904.mzid"}, {"accession": "MS:1002849", "name": "Search engine output file URI", "value": "ftp://ftp.pride.ebi.ac.uk/pride/data/archive/2019/11/PXD013003/F004905.mzid"}, {"accession": "MS:1002849", "name": "Search engine output file URI", "value": "ftp://ftp.pride.ebi.ac.uk/pride/data/archive/2019/11/PXD013003/F004906.mzid"}, {"accession": "MS:1002849", "name": "Search engine output file URI", "value": "ftp://ftp.pride.ebi.ac.uk/pride/data/archive/2019/11/PXD013003/F004907.mzid"}, {"accession": "MS:1002849", "name": "Search engine output file URI", "value": "ftp://ftp.pride.ebi.ac.uk/pride/data/archive/2019/11/PXD013003/F004908.mzid"}, {"accession": "MS:1002849", "name": "Search engine output file URI", "value": "ftp://ftp.pride.ebi.ac.uk/pride/data/archive/2019/11/PXD013003/F004909.mzid"}, {"accession": "MS:1002849", "name": "Search engine output file URI", "value": "ftp://ftp.pride.ebi.ac.uk/pride/data/archive/2019/11/PXD013003/F004910.mzid"}, {"accession": "MS:1002849", "name": "Search engine output file URI", "value": "ftp://ftp.pride.ebi.ac.uk/pride/data/archive/2019/11/PXD013003/F004911.mzid"}, {"accession": "MS:1002849", "name": "Search engine output file URI", "value": "ftp://ftp.pride.ebi.ac.uk/pride/data/archive/2019/11/PXD013003/F004912.mzid"}, {"accession": "MS:1002849", "name": "Search engine output file URI", "value": "ftp://ftp.pride.ebi.ac.uk/pride/data/archive/2019/11/PXD013003/F004913.mzid"}, {"accession": "MS:1002849", "name": "Search engine output file URI", "value": "ftp://ftp.pride.ebi.ac.uk/pride/data/archive/2019/11/PXD013003/F004914.mzid"}, {"accession": "MS:1002849", "name": "Search engine output file URI", "value": "ftp://ftp.pride.ebi.ac.uk/pride/data/archive/2019/11/PXD013003/F005642.mzid"}, {"accession": "MS:1002849", "name": "Search engine output file URI", "value": "ftp://ftp.pride.ebi.ac.uk/pride/data/archive/2019/11/PXD013003/F005643.mzid"}, {"accession": "MS:1002849", "name": "Search engine output file URI", "value": "ftp://ftp.pride.ebi.ac.uk/pride/data/archive/2019/11/PXD013003/F005644.mzid"}, {"accession": "MS:1002849", "name": "Search engine output file URI", "value": "ftp://ftp.pride.ebi.ac.uk/pride/data/archive/2019/11/PXD013003/F005645.mzid"}, {"accession": "MS:1002849", "name": "Search engine output file URI", "value": "ftp://ftp.pride.ebi.ac.uk/pride/data/archive/2019/11/PXD013003/F005646.mzid"}, {"accession": "MS:1002849", "name": "Search engine output file URI", "value": "ftp://ftp.pride.ebi.ac.uk/pride/data/archive/2019/11/PXD013003/F005647.mzid"}, {"accession": "MS:1002849", "name": "Search engine output file URI", "value": "ftp://ftp.pride.ebi.ac.uk/pride/data/archive/2019/11/PXD013003/F005648.mzid"}, {"accession": "MS:1002849", "name": "Search engine output file URI", "value": "ftp://ftp.pride.ebi.ac.uk/pride/data/archive/2019/11/PXD013003/F005654.mzid"}, {"accession": "MS:1002849", "name": "Search engine output file URI", "value": "ftp://ftp.pride.ebi.ac.uk/pride/data/archive/2019/11/PXD013003/F005655.mzid"}, {"accession": "MS:1002849", "name": "Search engine output file URI", "value": "ftp://ftp.pride.ebi.ac.uk/pride/data/archive/2019/11/PXD013003/F005656.mzid"}, {"accession": "MS:1002849", "name": "Search engine output file URI", "value": "ftp://ftp.pride.ebi.ac.uk/pride/data/archive/2019/11/PXD013003/F005657.mzid"}, {"accession": "MS:1002849", "name": "Search engine output file URI", "value": "ftp://ftp.pride.ebi.ac.uk/pride/data/archive/2019/11/PXD013003/F005658.mzid"}, {"accession": "MS:1002849", "name": "Search engine output file URI", "value": "ftp://ftp.pride.ebi.ac.uk/pride/data/archive/2019/11/PXD013003/F005659.mzid"}, {"accession": "MS:1002849", "name": "Search engine output file URI", "value": "ftp://ftp.pride.ebi.ac.uk/pride/data/archive/2019/11/PXD013003/F005660.mzid"}, {"accession": "MS:1002849", "name": "Search engine output file URI", "value": "ftp://ftp.pride.ebi.ac.uk/pride/data/archive/2019/11/PXD013003/F005661.mzid"}, {"accession": "MS:1002849", "name": "Search engine output file URI", "value": "ftp://ftp.pride.ebi.ac.uk/pride/data/archive/2019/11/PXD013003/F005662.mzid"}, {"accession": "MS:1002849", "name": "Search engine output file URI", "value": "ftp://ftp.pride.ebi.ac.uk/pride/data/archive/2019/11/PXD013003/F005663.mzid"}, {"accession": "MS:1002849", "name": "Search engine output file URI", "value": "ftp://ftp.pride.ebi.ac.uk/pride/data/archive/2019/11/PXD013003/F005664.mzid"}, {"accession": "MS:1002849", "name": "Search engine output file URI", "value": "ftp://ftp.pride.ebi.ac.uk/pride/data/archive/2019/11/PXD013003/F005665.mzid"}, {"accession": "MS:1002849", "name": "Search engine output file URI", "value": "ftp://ftp.pride.ebi.ac.uk/pride/data/archive/2019/11/PXD013003/F005666.mzid"}, {"accession": "MS:1002849", "name": "Search engine output file URI", "value": "ftp://ftp.pride.ebi.ac.uk/pride/data/archive/2019/11/PXD013003/F005667.mzid"}, {"accession": "MS:1002849", "name": "Search engine output file URI", "value": "ftp://ftp.pride.ebi.ac.uk/pride/data/archive/2019/11/PXD013003/F005668.mzid"}, {"accession": "MS:1002849", "name": "Search engine output file URI", "value": "ftp://ftp.pride.ebi.ac.uk/pride/data/archive/2019/11/PXD013003/F005669.mzid"}, {"accession": "MS:1002849", "name": "Search engine output file URI", "value": "ftp://ftp.pride.ebi.ac.uk/pride/data/archive/2019/11/PXD013003/F005672.mzid"}, {"accession": "MS:1002849", "name": "Search engine output file URI", "value": "ftp://ftp.pride.ebi.ac.uk/pride/data/archive/2019/11/PXD013003/F005674.mzid"}, {"accession": "MS:1002849", "name": "Search engine output file URI", "value": "ftp://ftp.pride.ebi.ac.uk/pride/data/archive/2019/11/PXD013003/F005676.mzid"}, {"accession": "MS:1002849", "name": "Search engine output file URI", "value": "ftp://ftp.pride.ebi.ac.uk/pride/data/archive/2019/11/PXD013003/F005677.mzid"}, {"accession": "MS:1002849", "name": "Search engine output file URI", "value": "ftp://ftp.pride.ebi.ac.uk/pride/data/archive/2019/11/PXD013003/F005678.mzid"}, {"accession": "MS:1002849", "name": "Search engine output file URI", "value": "ftp://ftp.pride.ebi.ac.uk/pride/data/archive/2019/11/PXD013003/F005679.mzid"}, {"accession": "MS:1002849", "name": "Search engine output file URI", "value": "ftp://ftp.pride.ebi.ac.uk/pride/data/archive/2019/11/PXD013003/F005680.mzid"}, {"accession": "MS:1002849", "name": "Search engine output file URI", "value": "ftp://ftp.pride.ebi.ac.uk/pride/data/archive/2019/11/PXD013003/F005681.mzid"}, {"accession": "MS:1002849", "name": "Search engine output file URI", "value": "ftp://ftp.pride.ebi.ac.uk/pride/data/archive/2019/11/PXD013003/F005682.mzid"}, {"accession": "MS:1002849", "name": "Search engine output file URI", "value": "ftp://ftp.pride.ebi.ac.uk/pride/data/archive/2019/11/PXD013003/F006615.mzid"}, {"accession": "MS:1002849", "name": "Search engine output file URI", "value": "ftp://ftp.pride.ebi.ac.uk/pride/data/archive/2019/11/PXD013003/F006616.mzid"}, {"accession": "MS:1002849", "name": "Search engine output file URI", "value": "ftp://ftp.pride.ebi.ac.uk/pride/data/archive/2019/11/PXD013003/F006617.mzid"}, {"accession": "MS:1002849", "name": "Search engine output file URI", "value": "ftp://ftp.pride.ebi.ac.uk/pride/data/archive/2019/11/PXD013003/F006618.mzid"}, {"accession": "MS:1002849", "name": "Search engine output file URI", "value": "ftp://ftp.pride.ebi.ac.uk/pride/data/archive/2019/11/PXD013003/F006638.mzid"}, {"accession": "MS:1002849", "name": "Search engine output file URI", "value": "ftp://ftp.pride.ebi.ac.uk/pride/data/archive/2019/11/PXD013003/F006639.mzid"}, {"accession": "MS:1002849", "name": "Search engine output file URI", "value": "ftp://ftp.pride.ebi.ac.uk/pride/data/archive/2019/11/PXD013003/F006641.mzid"}, {"accession": "MS:1002849", "name": "Search engine output file URI", "value": "ftp://ftp.pride.ebi.ac.uk/pride/data/archive/2019/11/PXD013003/F006642.mzid"}, {"accession": "MS:1002849", "name": "Search engine output file URI", "value": "ftp://ftp.pride.ebi.ac.uk/pride/data/archive/2019/11/PXD013003/F006644.mzid"}, {"accession": "MS:1002849", "name": "Search engine output file URI", "value": "ftp://ftp.pride.ebi.ac.uk/pride/data/archive/2019/11/PXD013003/F006646.mzid"}, {"accession": "MS:1002849", "name": "Search engine output file URI", "value": "ftp://ftp.pride.ebi.ac.uk/pride/data/archive/2019/11/PXD013003/F006647.mzid"}, {"accession": "MS:1002849", "name": "Search engine output file URI", "value": "ftp://ftp.pride.ebi.ac.uk/pride/data/archive/2019/11/PXD013003/F006648.mzid"}, {"accession": "MS:1002849", "name": "Search engine output file URI", "value": "ftp://ftp.pride.ebi.ac.uk/pride/data/archive/2019/11/PXD013003/F006649.mzid"}, {"accession": "MS:1002849", "name": "Search engine output file URI", "value": "ftp://ftp.pride.ebi.ac.uk/pride/data/archive/2019/11/PXD013003/F006650.mzid"}, {"accession": "MS:1002849", "name": "Search engine output file URI", "value": "ftp://ftp.pride.ebi.ac.uk/pride/data/archive/2019/11/PXD013003/F006651.mzid"}, {"accession": "MS:1002849", "name": "Search engine output file URI", "value": "ftp://ftp.pride.ebi.ac.uk/pride/data/archive/2019/11/PXD013003/F006662.mzid"}, {"accession": "MS:1002849", "name": "Search engine output file URI", "value": "ftp://ftp.pride.ebi.ac.uk/pride/data/archive/2019/11/PXD013003/F006663.mzid"}, {"accession": "MS:1002849", "name": "Search engine output file URI", "value": "ftp://ftp.pride.ebi.ac.uk/pride/data/archive/2019/11/PXD013003/F006664.mzid"}, {"accession": "MS:1002849", "name": "Search engine output file URI", "value": "ftp://ftp.pride.ebi.ac.uk/pride/data/archive/2019/11/PXD013003/F006665.mzid"}, {"accession": "MS:1002849", "name": "Search engine output file URI", "value": "ftp://ftp.pride.ebi.ac.uk/pride/data/archive/2019/11/PXD013003/F006666.mzid"}, {"accession": "MS:1002849", "name": "Search engine output file URI", "value": "ftp://ftp.pride.ebi.ac.uk/pride/data/archive/2019/11/PXD013003/F006667.mzid"}, {"accession": "MS:1002849", "name": "Search engine output file URI", "value": "ftp://ftp.pride.ebi.ac.uk/pride/data/archive/2019/11/PXD013003/F006668.mzid"}, {"accession": "MS:1002849", "name": "Search engine output file URI", "value": "ftp://ftp.pride.ebi.ac.uk/pride/data/archive/2019/11/PXD013003/F006669.mzid"}, {"accession": "MS:1002849", "name": "Search engine output file URI", "value": "ftp://ftp.pride.ebi.ac.uk/pride/data/archive/2019/11/PXD013003/F006670.mzid"}, {"accession": "MS:1002849", "name": "Search engine output file URI", "value": "ftp://ftp.pride.ebi.ac.uk/pride/data/archive/2019/11/PXD013003/F006671.mzid"}, {"accession": "MS:1002849", "name": "Search engine output file URI", "value": "ftp://ftp.pride.ebi.ac.uk/pride/data/archive/2019/11/PXD013003/F006672.mzid"}, {"accession": "MS:1002849", "name": "Search engine output file URI", "value": "ftp://ftp.pride.ebi.ac.uk/pride/data/archive/2019/11/PXD013003/F006673.mzid"}, {"accession": "MS:1002849", "name": "Search engine output file URI", "value": "ftp://ftp.pride.ebi.ac.uk/pride/data/archive/2019/11/PXD013003/F006674.mzid"}, {"accession": "MS:1002849", "name": "Search engine output file URI", "value": "ftp://ftp.pride.ebi.ac.uk/pride/data/archive/2019/11/PXD013003/F006675.mzid"}, {"accession": "MS:1002849", "name": "Search engine output file URI", "value": "ftp://ftp.pride.ebi.ac.uk/pride/data/archive/2019/11/PXD013003/F006676.mzid"}, {"accession": "MS:1002849", "name": "Search engine output file URI", "value": "ftp://ftp.pride.ebi.ac.uk/pride/data/archive/2019/11/PXD013003/F006677.mzid"}, {"accession": "MS:1002849", "name": "Search engine output file URI", "value": "ftp://ftp.pride.ebi.ac.uk/pride/data/archive/2019/11/PXD013003/F006678.mzid"}, {"accession": "MS:1002849", "name": "Search engine output file URI", "value": "ftp://ftp.pride.ebi.ac.uk/pride/data/archive/2019/11/PXD013003/F008484.mzid"}, {"accession": "MS:1002849", "name": "Search engine output file URI", "value": "ftp://ftp.pride.ebi.ac.uk/pride/data/archive/2019/11/PXD013003/F008485.mzid"}, {"accession": "MS:1002849", "name": "Search engine output file URI", "value": "ftp://ftp.pride.ebi.ac.uk/pride/data/archive/2019/11/PXD013003/F008486.mzid"}, {"accession": "MS:1002849", "name": "Search engine output file URI", "value": "ftp://ftp.pride.ebi.ac.uk/pride/data/archive/2019/11/PXD013003/F008487.mzid"}, {"accession": "MS:1002849", "name": "Search engine output file URI", "value": "ftp://ftp.pride.ebi.ac.uk/pride/data/archive/2019/11/PXD013003/F008488.mzid"}, {"accession": "MS:1002849", "name": "Search engine output file URI", "value": "ftp://ftp.pride.ebi.ac.uk/pride/data/archive/2019/11/PXD013003/F008489.mzid"}, {"accession": "MS:1002849", "name": "Search engine output file URI", "value": "ftp://ftp.pride.ebi.ac.uk/pride/data/archive/2019/11/PXD013003/F008490.mzid"}, {"accession": "MS:1002849", "name": "Search engine output file URI", "value": "ftp://ftp.pride.ebi.ac.uk/pride/data/archive/2019/11/PXD013003/F008491.mzid"}, {"accession": "MS:1002849", "name": "Search engine output file URI", "value": "ftp://ftp.pride.ebi.ac.uk/pride/data/archive/2019/11/PXD013003/F008492.mzid"}, {"accession": "MS:1002849", "name": "Search engine output file URI", "value": "ftp://ftp.pride.ebi.ac.uk/pride/data/archive/2019/11/PXD013003/F008493.mzid"}, {"accession": "MS:1002849", "name": "Search engine output file URI", "value": "ftp://ftp.pride.ebi.ac.uk/pride/data/archive/2019/11/PXD013003/F008494.mzid"}, {"accession": "MS:1002849", "name": "Search engine output file URI", "value": "ftp://ftp.pride.ebi.ac.uk/pride/data/archive/2019/11/PXD013003/F008495.mzid"}, {"accession": "MS:1002849", "name": "Search engine output file URI", "value": "ftp://ftp.pride.ebi.ac.uk/pride/data/archive/2019/11/PXD013003/F008496.mzid"}, {"accession": "MS:1002849", "name": "Search engine output file URI", "value": "ftp://ftp.pride.ebi.ac.uk/pride/data/archive/2019/11/PXD013003/F008497.mzid"}, {"accession": "MS:1002849", "name": "Search engine output file URI", "value": "ftp://ftp.pride.ebi.ac.uk/pride/data/archive/2019/11/PXD013003/F008498.mzid"}, {"accession": "MS:1002849", "name": "Search engine output file URI", "value": "ftp://ftp.pride.ebi.ac.uk/pride/data/archive/2019/11/PXD013003/F008499.mzid"}, {"accession": "MS:1002849", "name": "Search engine output file URI", "value": "ftp://ftp.pride.ebi.ac.uk/pride/data/archive/2019/11/PXD013003/F008500.mzid"}, {"accession": "MS:1002849", "name": "Search engine output file URI", "value": "ftp://ftp.pride.ebi.ac.uk/pride/data/archive/2019/11/PXD013003/F008501.mzid"}, {"accession": "MS:1002849", "name": "Search engine output file URI", "value": "ftp://ftp.pride.ebi.ac.uk/pride/data/archive/2019/11/PXD013003/F008502.mzid"}, {"accession": "MS:1002849", "name": "Search engine output file URI", "value": "ftp://ftp.pride.ebi.ac.uk/pride/data/archive/2019/11/PXD013003/F008504.mzid"}, {"accession": "MS:1002849", "name": "Search engine output file URI", "value": "ftp://ftp.pride.ebi.ac.uk/pride/data/archive/2019/11/PXD013003/F008510.mzid"}, {"accession": "MS:1002849", "name": "Search engine output file URI", "value": "ftp://ftp.pride.ebi.ac.uk/pride/data/archive/2019/11/PXD013003/F008512.mzid"}, {"accession": "MS:1002849", "name": "Search engine output file URI", "value": "ftp://ftp.pride.ebi.ac.uk/pride/data/archive/2019/11/PXD013003/F008513.mzid"}, {"accession": "MS:1002849", "name": "Search engine output file URI", "value": "ftp://ftp.pride.ebi.ac.uk/pride/data/archive/2019/11/PXD013003/F008514.mzid"}, {"accession": "MS:1002849", "name": "Search engine output file URI", "value": "ftp://ftp.pride.ebi.ac.uk/pride/data/archive/2019/11/PXD013003/F008515.mzid"}, {"accession": "MS:1002849", "name": "Search engine output file URI", "value": "ftp://ftp.pride.ebi.ac.uk/pride/data/archive/2019/11/PXD013003/F008553.mzid"}, {"accession": "MS:1002849", "name": "Search engine output file URI", "value": "ftp://ftp.pride.ebi.ac.uk/pride/data/archive/2019/11/PXD013003/F008556.mzid"}, {"accession": "MS:1002849", "name": "Search engine output file URI", "value": "ftp://ftp.pride.ebi.ac.uk/pride/data/archive/2019/11/PXD013003/F008557.mzid"}, {"accession": "MS:1002849", "name": "Search engine output file URI", "value": "ftp://ftp.pride.ebi.ac.uk/pride/data/archive/2019/11/PXD013003/F008558.mzid"}, {"accession": "MS:1002849", "name": "Search engine output file URI", "value": "ftp://ftp.pride.ebi.ac.uk/pride/data/archive/2019/11/PXD013003/F008559.mzid"}, {"accession": "MS:1002849", "name": "Search engine output file URI", "value": "ftp://ftp.pride.ebi.ac.uk/pride/data/archive/2019/11/PXD013003/F008560.mzid"}, {"accession": "MS:1002849", "name": "Search engine output file URI", "value": "ftp://ftp.pride.ebi.ac.uk/pride/data/archive/2019/11/PXD013003/F008561.mzid"}, {"accession": "MS:1002849", "name": "Search engine output file URI", "value": "ftp://ftp.pride.ebi.ac.uk/pride/data/archive/2019/11/PXD013003/F009367.mzid"}, {"accession": "MS:1002849", "name": "Search engine output file URI", "value": "ftp://ftp.pride.ebi.ac.uk/pride/data/archive/2019/11/PXD013003/F009368.mzid"}, {"accession": "MS:1002849", "name": "Search engine output file URI", "value": "ftp://ftp.pride.ebi.ac.uk/pride/data/archive/2019/11/PXD013003/F009369.mzid"}, {"accession": "MS:1002849", "name": "Search engine output file URI", "value": "ftp://ftp.pride.ebi.ac.uk/pride/data/archive/2019/11/PXD013003/F009370.mzid"}, {"accession": "MS:1002849", "name": "Search engine output file URI", "value": "ftp://ftp.pride.ebi.ac.uk/pride/data/archive/2019/11/PXD013003/F009371.mzid"}, {"accession": "MS:1002849", "name": "Search engine output file URI", "value": "ftp://ftp.pride.ebi.ac.uk/pride/data/archive/2019/11/PXD013003/F009372.mzid"}, {"accession": "MS:1002849", "name": "Search engine output file URI", "value": "ftp://ftp.pride.ebi.ac.uk/pride/data/archive/2019/11/PXD013003/F009373.mzid"}, {"accession": "MS:1002849", "name": "Search engine output file URI", "value": "ftp://ftp.pride.ebi.ac.uk/pride/data/archive/2019/11/PXD013003/F009374.mzid"}, {"accession": "MS:1002849", "name": "Search engine output file URI", "value": "ftp://ftp.pride.ebi.ac.uk/pride/data/archive/2019/11/PXD013003/F009375.mzid"}, {"accession": "MS:1002849", "name": "Search engine output file URI", "value": "ftp://ftp.pride.ebi.ac.uk/pride/data/archive/2019/11/PXD013003/F009376.mzid"}, {"accession": "MS:1002849", "name": "Search engine output file URI", "value": "ftp://ftp.pride.ebi.ac.uk/pride/data/archive/2019/11/PXD013003/F009377.mzid"}, {"accession": "MS:1002849", "name": "Search engine output file URI", "value": "ftp://ftp.pride.ebi.ac.uk/pride/data/archive/2019/11/PXD013003/F009378.mzid"}, {"accession": "MS:1002849", "name": "Search engine output file URI", "value": "ftp://ftp.pride.ebi.ac.uk/pride/data/archive/2019/11/PXD013003/F009379.mzid"}, {"accession": "MS:1002849", "name": "Search engine output file URI", "value": "ftp://ftp.pride.ebi.ac.uk/pride/data/archive/2019/11/PXD013003/F009380.mzid"}, {"accession": "MS:1002849", "name": "Search engine output file URI", "value": "ftp://ftp.pride.ebi.ac.uk/pride/data/archive/2019/11/PXD013003/F009381.mzid"}, {"accession": "MS:1002849", "name": "Search engine output file URI", "value": "ftp://ftp.pride.ebi.ac.uk/pride/data/archive/2019/11/PXD013003/F009382.mzid"}, {"accession": "MS:1002849", "name": "Search engine output file URI", "value": "ftp://ftp.pride.ebi.ac.uk/pride/data/archive/2019/11/PXD013003/F009601.mzid"}, {"accession": "MS:1002849", "name": "Search engine output file URI", "value": "ftp://ftp.pride.ebi.ac.uk/pride/data/archive/2019/11/PXD013003/F009602.mzid"}, {"accession": "MS:1002849", "name": "Search engine output file URI", "value": "ftp://ftp.pride.ebi.ac.uk/pride/data/archive/2019/11/PXD013003/F009603.mzid"}, {"accession": "MS:1002849", "name": "Search engine output file URI", "value": "ftp://ftp.pride.ebi.ac.uk/pride/data/archive/2019/11/PXD013003/F009604.mzid"}, {"accession": "MS:1002849", "name": "Search engine output file URI", "value": "ftp://ftp.pride.ebi.ac.uk/pride/data/archive/2019/11/PXD013003/F009606.mzid"}, {"accession": "MS:1002849", "name": "Search engine output file URI", "value": "ftp://ftp.pride.ebi.ac.uk/pride/data/archive/2019/11/PXD013003/F009607.mzid"}, {"accession": "MS:1002849", "name": "Search engine output file URI", "value": "ftp://ftp.pride.ebi.ac.uk/pride/data/archive/2019/11/PXD013003/F009608.mzid"}, {"accession": "MS:1002849", "name": "Search engine output file URI", "value": "ftp://ftp.pride.ebi.ac.uk/pride/data/archive/2019/11/PXD013003/F009609.mzid"}, {"accession": "MS:1002850", "name": "Peak list file URI", "value": "ftp://ftp.pride.ebi.ac.uk/pride/data/archive/2019/11/PXD013003/06b9cd898d6ebb8f___QE1_Katja_Exp7_sample1A.raw.-1.mgf"}, {"accession": "MS:1002850", "name": "Peak list file URI", "value": "ftp://ftp.pride.ebi.ac.uk/pride/data/archive/2019/11/PXD013003/06b9cd898d6ebb8f___QE1_Katja_Exp7_sample1A_R.raw.-1.mgf"}, {"accession": "MS:1002850", "name": "Peak list file URI", "value": "ftp://ftp.pride.ebi.ac.uk/pride/data/archive/2019/11/PXD013003/06b9cd898d6ebb8f___QE1_Katja_Exp7_sample1B.raw.-1.mgf"}, {"accession": "MS:1002850", "name": "Peak list file URI", "value": "ftp://ftp.pride.ebi.ac.uk/pride/data/archive/2019/11/PXD013003/06b9cd898d6ebb8f___QE1_Katja_Exp7_sample1B_R.raw.-1.mgf"}, {"accession": "MS:1002850", "name": "Peak list file URI", "value": "ftp://ftp.pride.ebi.ac.uk/pride/data/archive/2019/11/PXD013003/06b9cd898d6ebb8f___QE1_Katja_Exp7_sample2A.raw.-1.mgf"}, {"accession": "MS:1002850", "name": "Peak list file URI", "value": "ftp://ftp.pride.ebi.ac.uk/pride/data/archive/2019/11/PXD013003/06b9cd898d6ebb8f___QE1_Katja_Exp7_sample2A_R.raw.-1.mgf"}, {"accession": "MS:1002850", "name": "Peak list file URI", "value": "ftp://ftp.pride.ebi.ac.uk/pride/data/archive/2019/11/PXD013003/06b9cd898d6ebb8f___QE1_Katja_Exp7_sample2B.raw.-1.mgf"}, {"accession": "MS:1002850", "name": "Peak list file URI", "value": "ftp://ftp.pride.ebi.ac.uk/pride/data/archive/2019/11/PXD013003/06b9cd898d6ebb8f___QE1_Katja_Exp7_sample2B_R.raw.-1.mgf"}, {"accession": "MS:1002850", "name": "Peak list file URI", "value": "ftp://ftp.pride.ebi.ac.uk/pride/data/archive/2019/11/PXD013003/06b9cd898d6ebb8f___QE1_Katja_Exp7_sample3A.raw.-1.mgf"}, {"accession": "MS:1002850", "name": "Peak list file URI", "value": "ftp://ftp.pride.ebi.ac.uk/pride/data/archive/2019/11/PXD013003/06b9cd898d6ebb8f___QE1_Katja_Exp7_sample3A_R.raw.-1.mgf"}, {"accession": "MS:1002850", "name": "Peak list file URI", "value": "ftp://ftp.pride.ebi.ac.uk/pride/data/archive/2019/11/PXD013003/06b9cd898d6ebb8f___QE1_Katja_Exp7_sample3B.raw.-1.mgf"}, {"accession": "MS:1002850", "name": "Peak list file URI", "value": "ftp://ftp.pride.ebi.ac.uk/pride/data/archive/2019/11/PXD013003/06b9cd898d6ebb8f___QE1_Katja_Exp7_sample3B_R.raw.-1.mgf"}, {"accession": "MS:1002850", "name": "Peak list file URI", "value": "ftp://ftp.pride.ebi.ac.uk/pride/data/archive/2019/11/PXD013003/06b9cd898d6ebb8f___QE1_Katja_Exp7_sample4A.raw.-1.mgf"}, {"accession": "MS:1002850", "name": "Peak list file URI", "value": "ftp://ftp.pride.ebi.ac.uk/pride/data/archive/2019/11/PXD013003/06b9cd898d6ebb8f___QE1_Katja_Exp7_sample4A_R.raw.-1.mgf"}, {"accession": "MS:1002850", "name": "Peak list file URI", "value": "ftp://ftp.pride.ebi.ac.uk/pride/data/archive/2019/11/PXD013003/06b9cd898d6ebb8f___QE1_Katja_Exp7_sample4B.raw.-1.mgf"}, {"accession": "MS:1002850", "name": "Peak list file URI", "value": "ftp://ftp.pride.ebi.ac.uk/pride/data/archive/2019/11/PXD013003/06b9cd898d6ebb8f___QE1_Katja_Exp7_sample4B_R.raw.-1.mgf"}, {"accession": "MS:1002850", "name": "Peak list file URI", "value": "ftp://ftp.pride.ebi.ac.uk/pride/data/archive/2019/11/PXD013003/3b0b09618ba7bda8___Katja_Exp6_Sample6_1a.raw.-1.mgf"}, {"accession": "MS:1002850", "name": "Peak list file URI", "value": "ftp://ftp.pride.ebi.ac.uk/pride/data/archive/2019/11/PXD013003/3b0b09618ba7bda8___Katja_Exp6_Sample6_1a_R.raw.-1.mgf"}, {"accession": "MS:1002850", "name": "Peak list file URI", "value": "ftp://ftp.pride.ebi.ac.uk/pride/data/archive/2019/11/PXD013003/3b0b09618ba7bda8___Katja_Exp6_Sample6_1b.raw.-1.mgf"}, {"accession": "MS:1002850", "name": "Peak list file URI", "value": "ftp://ftp.pride.ebi.ac.uk/pride/data/archive/2019/11/PXD013003/3b0b09618ba7bda8___Katja_Exp6_Sample6_1b_R.raw.-1.mgf"}, {"accession": "MS:1002850", "name": "Peak list file URI", "value": "ftp://ftp.pride.ebi.ac.uk/pride/data/archive/2019/11/PXD013003/3b0b09618ba7bda8___Katja_Exp6_Sample6_2a.raw.-1.mgf"}, {"accession": "MS:1002850", "name": "Peak list file URI", "value": "ftp://ftp.pride.ebi.ac.uk/pride/data/archive/2019/11/PXD013003/3b0b09618ba7bda8___Katja_Exp6_Sample6_2a_R.raw.-1.mgf"}, {"accession": "MS:1002850", "name": "Peak list file URI", "value": "ftp://ftp.pride.ebi.ac.uk/pride/data/archive/2019/11/PXD013003/3b0b09618ba7bda8___Katja_Exp6_Sample6_3a.raw.-1.mgf"}, {"accession": "MS:1002850", "name": "Peak list file URI", "value": "ftp://ftp.pride.ebi.ac.uk/pride/data/archive/2019/11/PXD013003/3b0b09618ba7bda8___Katja_Exp6_Sample6_3a_R.raw.-1.mgf"}, {"accession": "MS:1002850", "name": "Peak list file URI", "value": "ftp://ftp.pride.ebi.ac.uk/pride/data/archive/2019/11/PXD013003/3b0b09618ba7bda8___Katja_Exp6_Sample6_4a.raw.-1.mgf"}, {"accession": "MS:1002850", "name": "Peak list file URI", "value": "ftp://ftp.pride.ebi.ac.uk/pride/data/archive/2019/11/PXD013003/3b0b09618ba7bda8___Katja_Exp6_Sample6_4a_R.raw.-1.mgf"}, {"accession": "MS:1002850", "name": "Peak list file URI", "value": "ftp://ftp.pride.ebi.ac.uk/pride/data/archive/2019/11/PXD013003/3b0b09618ba7bda8___Katja_Exp6_Sample6_5a.raw.-1.mgf"}, {"accession": "MS:1002850", "name": "Peak list file URI", "value": "ftp://ftp.pride.ebi.ac.uk/pride/data/archive/2019/11/PXD013003/3b0b09618ba7bda8___Katja_Exp6_Sample6_5a_R.raw.-1.mgf"}, {"accession": "MS:1002850", "name": "Peak list file URI", "value": "ftp://ftp.pride.ebi.ac.uk/pride/data/archive/2019/11/PXD013003/3b0b09618ba7bda8___Katja_Exp6_Sample6_6a.raw.-1.mgf"}, {"accession": "MS:1002850", "name": "Peak list file URI", "value": "ftp://ftp.pride.ebi.ac.uk/pride/data/archive/2019/11/PXD013003/3b0b09618ba7bda8___Katja_Exp6_Sample6_6a_R.raw.-1.mgf"}, {"accession": "MS:1002850", "name": "Peak list file URI", "value": "ftp://ftp.pride.ebi.ac.uk/pride/data/archive/2019/11/PXD013003/3b0b09618ba7bda8___Katja_Exp6_Sample6_7a.raw.-1.mgf"}, {"accession": "MS:1002850", "name": "Peak list file URI", "value": "ftp://ftp.pride.ebi.ac.uk/pride/data/archive/2019/11/PXD013003/3b0b09618ba7bda8___Katja_Exp6_Sample6_7a_R.raw.-1.mgf"}, {"accession": "MS:1002850", "name": "Peak list file URI", "value": "ftp://ftp.pride.ebi.ac.uk/pride/data/archive/2019/11/PXD013003/3b0b09618ba7bda8___Katja_Exp6_Sample6_8a.raw.-1.mgf"}, {"accession": "MS:1002850", "name": "Peak list file URI", "value": "ftp://ftp.pride.ebi.ac.uk/pride/data/archive/2019/11/PXD013003/3b0b09618ba7bda8___Katja_Exp6_Sample6_8a_R.raw.-1.mgf"}, {"accession": "MS:1002850", "name": "Peak list file URI", "value": "ftp://ftp.pride.ebi.ac.uk/pride/data/archive/2019/11/PXD013003/40ed83523ea17e2c___QE1_Katja_Exp7_sample8A.raw.-1.mgf"}, {"accession": "MS:1002850", "name": "Peak list file URI", "value": "ftp://ftp.pride.ebi.ac.uk/pride/data/archive/2019/11/PXD013003/40ed83523ea17e2c___QE1_Katja_Exp7_sample8A_R.raw.-1.mgf"}, {"accession": "MS:1002850", "name": "Peak list file URI", "value": "ftp://ftp.pride.ebi.ac.uk/pride/data/archive/2019/11/PXD013003/40ed83523ea17e2c___QE1_Katja_Exp8_sample1A.raw.-1.mgf"}, {"accession": "MS:1002850", "name": "Peak list file URI", "value": "ftp://ftp.pride.ebi.ac.uk/pride/data/archive/2019/11/PXD013003/40ed83523ea17e2c___QE1_Katja_Exp8_sample1A_R.raw.-1.mgf"}, {"accession": "MS:1002850", "name": "Peak list file URI", "value": "ftp://ftp.pride.ebi.ac.uk/pride/data/archive/2019/11/PXD013003/40ed83523ea17e2c___QE1_Katja_Exp8_sample1B.raw.-1.mgf"}, {"accession": "MS:1002850", "name": "Peak list file URI", "value": "ftp://ftp.pride.ebi.ac.uk/pride/data/archive/2019/11/PXD013003/40ed83523ea17e2c___QE1_Katja_Exp8_sample1B_R.raw.-1.mgf"}, {"accession": "MS:1002850", "name": "Peak list file URI", "value": "ftp://ftp.pride.ebi.ac.uk/pride/data/archive/2019/11/PXD013003/40ed83523ea17e2c___QE1_Katja_Exp8_sample2A.raw.-1.mgf"}, {"accession": "MS:1002850", "name": "Peak list file URI", "value": "ftp://ftp.pride.ebi.ac.uk/pride/data/archive/2019/11/PXD013003/40ed83523ea17e2c___QE1_Katja_Exp8_sample2A_R.raw.-1.mgf"}, {"accession": "MS:1002850", "name": "Peak list file URI", "value": "ftp://ftp.pride.ebi.ac.uk/pride/data/archive/2019/11/PXD013003/40ed83523ea17e2c___QE1_Katja_Exp8_sample2B.raw.-1.mgf"}, {"accession": "MS:1002850", "name": "Peak list file URI", "value": "ftp://ftp.pride.ebi.ac.uk/pride/data/archive/2019/11/PXD013003/40ed83523ea17e2c___QE1_Katja_Exp8_sample2B_R.raw.-1.mgf"}, {"accession": "MS:1002850", "name": "Peak list file URI", "value": "ftp://ftp.pride.ebi.ac.uk/pride/data/archive/2019/11/PXD013003/40ed83523ea17e2c___QE1_Katja_Exp8_sample3A.raw.-1.mgf"}, {"accession": "MS:1002850", "name": "Peak list file URI", "value": "ftp://ftp.pride.ebi.ac.uk/pride/data/archive/2019/11/PXD013003/40ed83523ea17e2c___QE1_Katja_Exp8_sample3A_R.raw.-1.mgf"}, {"accession": "MS:1002850", "name": "Peak list file URI", "value": "ftp://ftp.pride.ebi.ac.uk/pride/data/archive/2019/11/PXD013003/40ed83523ea17e2c___QE1_Katja_Exp8_sample3B.raw.-1.mgf"}, {"accession": "MS:1002850", "name": "Peak list file URI", "value": "ftp://ftp.pride.ebi.ac.uk/pride/data/archive/2019/11/PXD013003/40ed83523ea17e2c___QE1_Katja_Exp8_sample3B_R.raw.-1.mgf"}, {"accession": "MS:1002850", "name": "Peak list file URI", "value": "ftp://ftp.pride.ebi.ac.uk/pride/data/archive/2019/11/PXD013003/40ed83523ea17e2c___QE1_Katja_Exp8_sample4A.raw.-1.mgf"}, {"accession": "MS:1002850", "name": "Peak list file URI", "value": "ftp://ftp.pride.ebi.ac.uk/pride/data/archive/2019/11/PXD013003/40ed83523ea17e2c___QE1_Katja_Exp8_sample4A_R.raw.-1.mgf"}, {"accession": "MS:1002850", "name": "Peak list file URI", "value": "ftp://ftp.pride.ebi.ac.uk/pride/data/archive/2019/11/PXD013003/40ed83523ea17e2c___QE1_Katja_Exp8_sample4B.raw.-1.mgf"}, {"accession": "MS:1002850", "name": "Peak list file URI", "value": "ftp://ftp.pride.ebi.ac.uk/pride/data/archive/2019/11/PXD013003/40ed83523ea17e2c___QE1_Katja_Exp8_sample4B_R.raw.-1.mgf"}, {"accession": "MS:1002850", "name": "Peak list file URI", "value": "ftp://ftp.pride.ebi.ac.uk/pride/data/archive/2019/11/PXD013003/40ed83523ea17e2c___QE1_Katja_Exp8_sample5A.raw.-1.mgf"}, {"accession": "MS:1002850", "name": "Peak list file URI", "value": "ftp://ftp.pride.ebi.ac.uk/pride/data/archive/2019/11/PXD013003/40ed83523ea17e2c___QE1_Katja_Exp8_sample5A_R.raw.-1.mgf"}, {"accession": "MS:1002850", "name": "Peak list file URI", "value": "ftp://ftp.pride.ebi.ac.uk/pride/data/archive/2019/11/PXD013003/40ed83523ea17e2c___QE1_Katja_Exp8_sample5B.raw.-1.mgf"}, {"accession": "MS:1002850", "name": "Peak list file URI", "value": "ftp://ftp.pride.ebi.ac.uk/pride/data/archive/2019/11/PXD013003/40ed83523ea17e2c___QE1_Katja_Exp8_sample5B_R.raw.-1.mgf"}, {"accession": "MS:1002850", "name": "Peak list file URI", "value": "ftp://ftp.pride.ebi.ac.uk/pride/data/archive/2019/11/PXD013003/40ed83523ea17e2c___QE1_Katja_Exp8_sample6A.raw.-1.mgf"}, {"accession": "MS:1002850", "name": "Peak list file URI", "value": "ftp://ftp.pride.ebi.ac.uk/pride/data/archive/2019/11/PXD013003/40ed83523ea17e2c___QE1_Katja_Exp8_sample6A_R.raw.-1.mgf"}, {"accession": "MS:1002850", "name": "Peak list file URI", "value": "ftp://ftp.pride.ebi.ac.uk/pride/data/archive/2019/11/PXD013003/40ed83523ea17e2c___QE1_Katja_Exp8_sample6B.raw.-1.mgf"}, {"accession": "MS:1002850", "name": "Peak list file URI", "value": "ftp://ftp.pride.ebi.ac.uk/pride/data/archive/2019/11/PXD013003/40ed83523ea17e2c___QE1_Katja_Exp8_sample6B_R.raw.-1.mgf"}, {"accession": "MS:1002850", "name": "Peak list file URI", "value": "ftp://ftp.pride.ebi.ac.uk/pride/data/archive/2019/11/PXD013003/40ed83523ea17e2c___QE1_Katja_Exp8_sample7A.raw.-1.mgf"}, {"accession": "MS:1002850", "name": "Peak list file URI", "value": "ftp://ftp.pride.ebi.ac.uk/pride/data/archive/2019/11/PXD013003/40ed83523ea17e2c___QE1_Katja_Exp8_sample7A_R.raw.-1.mgf"}, {"accession": "MS:1002850", "name": "Peak list file URI", "value": "ftp://ftp.pride.ebi.ac.uk/pride/data/archive/2019/11/PXD013003/40ed83523ea17e2c___QE1_Katja_Exp8_sample7B_171116030750.raw.-1.mgf"}, {"accession": "MS:1002850", "name": "Peak list file URI", "value": "ftp://ftp.pride.ebi.ac.uk/pride/data/archive/2019/11/PXD013003/40ed83523ea17e2c___QE1_Katja_Exp8_sample7B_R.raw.-1.mgf"}, {"accession": "MS:1002850", "name": "Peak list file URI", "value": "ftp://ftp.pride.ebi.ac.uk/pride/data/archive/2019/11/PXD013003/40ed83523ea17e2c___QE1_Katja_Exp8_sample8B.raw.-1.mgf"}, {"accession": "MS:1002850", "name": "Peak list file URI", "value": "ftp://ftp.pride.ebi.ac.uk/pride/data/archive/2019/11/PXD013003/40ed83523ea17e2c___QE1_Katja_Exp8_sample8B_R.raw.-1.mgf"}, {"accession": "MS:1002850", "name": "Peak list file URI", "value": "ftp://ftp.pride.ebi.ac.uk/pride/data/archive/2019/11/PXD013003/4df4c51a7b6e6ae0___Katja_Exp6_Sample6_2b.raw.-1.mgf"}, {"accession": "MS:1002850", "name": "Peak list file URI", "value": "ftp://ftp.pride.ebi.ac.uk/pride/data/archive/2019/11/PXD013003/4df4c51a7b6e6ae0___Katja_Exp6_Sample6_2b_R.raw.-1.mgf"}, {"accession": "MS:1002850", "name": "Peak list file URI", "value": "ftp://ftp.pride.ebi.ac.uk/pride/data/archive/2019/11/PXD013003/4df4c51a7b6e6ae0___Katja_Exp6_Sample6_3b.raw.-1.mgf"}, {"accession": "MS:1002850", "name": "Peak list file URI", "value": "ftp://ftp.pride.ebi.ac.uk/pride/data/archive/2019/11/PXD013003/4df4c51a7b6e6ae0___Katja_Exp6_Sample6_3b_R.raw.-1.mgf"}, {"accession": "MS:1002850", "name": "Peak list file URI", "value": "ftp://ftp.pride.ebi.ac.uk/pride/data/archive/2019/11/PXD013003/4df4c51a7b6e6ae0___Katja_Exp6_Sample6_4b.raw.-1.mgf"}, {"accession": "MS:1002850", "name": "Peak list file URI", "value": "ftp://ftp.pride.ebi.ac.uk/pride/data/archive/2019/11/PXD013003/4df4c51a7b6e6ae0___Katja_Exp6_Sample6_4b_R.raw.-1.mgf"}, {"accession": "MS:1002850", "name": "Peak list file URI", "value": "ftp://ftp.pride.ebi.ac.uk/pride/data/archive/2019/11/PXD013003/4df4c51a7b6e6ae0___Katja_Exp6_Sample6_5b.raw.-1.mgf"}, {"accession": "MS:1002850", "name": "Peak list file URI", "value": "ftp://ftp.pride.ebi.ac.uk/pride/data/archive/2019/11/PXD013003/4df4c51a7b6e6ae0___Katja_Exp6_Sample6_5b_R.raw.-1.mgf"}, {"accession": "MS:1002850", "name": "Peak list file URI", "value": "ftp://ftp.pride.ebi.ac.uk/pride/data/archive/2019/11/PXD013003/4df4c51a7b6e6ae0___Katja_Exp6_Sample6_6b.raw.-1.mgf"}, {"accession": "MS:1002850", "name": "Peak list file URI", "value": "ftp://ftp.pride.ebi.ac.uk/pride/data/archive/2019/11/PXD013003/4df4c51a7b6e6ae0___Katja_Exp6_Sample6_6b_R.raw.-1.mgf"}, {"accession": "MS:1002850", "name": "Peak list file URI", "value": "ftp://ftp.pride.ebi.ac.uk/pride/data/archive/2019/11/PXD013003/4df4c51a7b6e6ae0___Katja_Exp6_Sample6_7b.raw.-1.mgf"}, {"accession": "MS:1002850", "name": "Peak list file URI", "value": "ftp://ftp.pride.ebi.ac.uk/pride/data/archive/2019/11/PXD013003/4df4c51a7b6e6ae0___Katja_Exp6_Sample6_7b_R.raw.-1.mgf"}, {"accession": "MS:1002850", "name": "Peak list file URI", "value": "ftp://ftp.pride.ebi.ac.uk/pride/data/archive/2019/11/PXD013003/4df4c51a7b6e6ae0___Katja_Exp6_Sample6_8b.raw.-1.mgf"}, {"accession": "MS:1002850", "name": "Peak list file URI", "value": "ftp://ftp.pride.ebi.ac.uk/pride/data/archive/2019/11/PXD013003/4df4c51a7b6e6ae0___Katja_Exp6_Sample6_8b_R.raw.-1.mgf"}, {"accession": "MS:1002850", "name": "Peak list file URI", "value": "ftp://ftp.pride.ebi.ac.uk/pride/data/archive/2019/11/PXD013003/629fb717df522b29___QE1_Katja_Exp10_sample7A.raw.-1.mgf"}, {"accession": "MS:1002850", "name": "Peak list file URI", "value": "ftp://ftp.pride.ebi.ac.uk/pride/data/archive/2019/11/PXD013003/629fb717df522b29___QE1_Katja_Exp10_sample7A_R.raw.-1.mgf"}, {"accession": "MS:1002850", "name": "Peak list file URI", "value": "ftp://ftp.pride.ebi.ac.uk/pride/data/archive/2019/11/PXD013003/629fb717df522b29___QE1_Katja_Exp10_sample7B.raw.-1.mgf"}, {"accession": "MS:1002850", "name": "Peak list file URI", "value": "ftp://ftp.pride.ebi.ac.uk/pride/data/archive/2019/11/PXD013003/629fb717df522b29___QE1_Katja_Exp10_sample7B_R.raw.-1.mgf"}, {"accession": "MS:1002850", "name": "Peak list file URI", "value": "ftp://ftp.pride.ebi.ac.uk/pride/data/archive/2019/11/PXD013003/629fb717df522b29___QE1_Katja_Exp10_sample8A.raw.-1.mgf"}, {"accession": "MS:1002850", "name": "Peak list file URI", "value": "ftp://ftp.pride.ebi.ac.uk/pride/data/archive/2019/11/PXD013003/629fb717df522b29___QE1_Katja_Exp10_sample8A_R.raw.-1.mgf"}, {"accession": "MS:1002850", "name": "Peak list file URI", "value": "ftp://ftp.pride.ebi.ac.uk/pride/data/archive/2019/11/PXD013003/629fb717df522b29___QE1_Katja_Exp10_sample8B.raw.-1.mgf"}, {"accession": "MS:1002850", "name": "Peak list file URI", "value": "ftp://ftp.pride.ebi.ac.uk/pride/data/archive/2019/11/PXD013003/629fb717df522b29___QE1_Katja_Exp10_sample8B_R.raw.-1.mgf"}, {"accession": "MS:1002850", "name": "Peak list file URI", "value": "ftp://ftp.pride.ebi.ac.uk/pride/data/archive/2019/11/PXD013003/7030e79fae26b51d___QE1_Katja_Exp9_sample1A.raw.-1.mgf"}, {"accession": "MS:1002850", "name": "Peak list file URI", "value": "ftp://ftp.pride.ebi.ac.uk/pride/data/archive/2019/11/PXD013003/7030e79fae26b51d___QE1_Katja_Exp9_sample1A_R.raw.-1.mgf"}, {"accession": "MS:1002850", "name": "Peak list file URI", "value": "ftp://ftp.pride.ebi.ac.uk/pride/data/archive/2019/11/PXD013003/7030e79fae26b51d___QE1_Katja_Exp9_sample1B.raw.-1.mgf"}, {"accession": "MS:1002850", "name": "Peak list file URI", "value": "ftp://ftp.pride.ebi.ac.uk/pride/data/archive/2019/11/PXD013003/7030e79fae26b51d___QE1_Katja_Exp9_sample1B_R.raw.-1.mgf"}, {"accession": "MS:1002850", "name": "Peak list file URI", "value": "ftp://ftp.pride.ebi.ac.uk/pride/data/archive/2019/11/PXD013003/7030e79fae26b51d___QE1_Katja_Exp9_sample2A.raw.-1.mgf"}, {"accession": "MS:1002850", "name": "Peak list file URI", "value": "ftp://ftp.pride.ebi.ac.uk/pride/data/archive/2019/11/PXD013003/7030e79fae26b51d___QE1_Katja_Exp9_sample2A_R.raw.-1.mgf"}, {"accession": "MS:1002850", "name": "Peak list file URI", "value": "ftp://ftp.pride.ebi.ac.uk/pride/data/archive/2019/11/PXD013003/7030e79fae26b51d___QE1_Katja_Exp9_sample2B.raw.-1.mgf"}, {"accession": "MS:1002850", "name": "Peak list file URI", "value": "ftp://ftp.pride.ebi.ac.uk/pride/data/archive/2019/11/PXD013003/7030e79fae26b51d___QE1_Katja_Exp9_sample2B_R.raw.-1.mgf"}, {"accession": "MS:1002850", "name": "Peak list file URI", "value": "ftp://ftp.pride.ebi.ac.uk/pride/data/archive/2019/11/PXD013003/7030e79fae26b51d___QE1_Katja_Exp9_sample3A.raw.-1.mgf"}, {"accession": "MS:1002850", "name": "Peak list file URI", "value": "ftp://ftp.pride.ebi.ac.uk/pride/data/archive/2019/11/PXD013003/7030e79fae26b51d___QE1_Katja_Exp9_sample3A_R.raw.-1.mgf"}, {"accession": "MS:1002850", "name": "Peak list file URI", "value": "ftp://ftp.pride.ebi.ac.uk/pride/data/archive/2019/11/PXD013003/7030e79fae26b51d___QE1_Katja_Exp9_sample3B.raw.-1.mgf"}, {"accession": "MS:1002850", "name": "Peak list file URI", "value": "ftp://ftp.pride.ebi.ac.uk/pride/data/archive/2019/11/PXD013003/7030e79fae26b51d___QE1_Katja_Exp9_sample3B_R.raw.-1.mgf"}, {"accession": "MS:1002850", "name": "Peak list file URI", "value": "ftp://ftp.pride.ebi.ac.uk/pride/data/archive/2019/11/PXD013003/7030e79fae26b51d___QE1_Katja_Exp9_sample4A.raw.-1.mgf"}, {"accession": "MS:1002850", "name": "Peak list file URI", "value": "ftp://ftp.pride.ebi.ac.uk/pride/data/archive/2019/11/PXD013003/7030e79fae26b51d___QE1_Katja_Exp9_sample4A_R.raw.-1.mgf"}, {"accession": "MS:1002850", "name": "Peak list file URI", "value": "ftp://ftp.pride.ebi.ac.uk/pride/data/archive/2019/11/PXD013003/7030e79fae26b51d___QE1_Katja_Exp9_sample4B.raw.-1.mgf"}, {"accession": "MS:1002850", "name": "Peak list file URI", "value": "ftp://ftp.pride.ebi.ac.uk/pride/data/archive/2019/11/PXD013003/7030e79fae26b51d___QE1_Katja_Exp9_sample4B_R.raw.-1.mgf"}, {"accession": "MS:1002850", "name": "Peak list file URI", "value": "ftp://ftp.pride.ebi.ac.uk/pride/data/archive/2019/11/PXD013003/83bc28059143c1d8___Katja_Exp3_Sample3_1.raw.-1.mgf"}, {"accession": "MS:1002850", "name": "Peak list file URI", "value": "ftp://ftp.pride.ebi.ac.uk/pride/data/archive/2019/11/PXD013003/83bc28059143c1d8___Katja_Exp3_Sample3_1_R.raw.-1.mgf"}, {"accession": "MS:1002850", "name": "Peak list file URI", "value": "ftp://ftp.pride.ebi.ac.uk/pride/data/archive/2019/11/PXD013003/83bc28059143c1d8___Katja_Exp3_Sample3_2.raw.-1.mgf"}, {"accession": "MS:1002850", "name": "Peak list file URI", "value": "ftp://ftp.pride.ebi.ac.uk/pride/data/archive/2019/11/PXD013003/83bc28059143c1d8___Katja_Exp3_Sample3_2_R.raw.-1.mgf"}, {"accession": "MS:1002850", "name": "Peak list file URI", "value": "ftp://ftp.pride.ebi.ac.uk/pride/data/archive/2019/11/PXD013003/83bc28059143c1d8___Katja_Exp3_Sample3_3.raw.-1.mgf"}, {"accession": "MS:1002850", "name": "Peak list file URI", "value": "ftp://ftp.pride.ebi.ac.uk/pride/data/archive/2019/11/PXD013003/83bc28059143c1d8___Katja_Exp3_Sample3_3_R.raw.-1.mgf"}, {"accession": "MS:1002850", "name": "Peak list file URI", "value": "ftp://ftp.pride.ebi.ac.uk/pride/data/archive/2019/11/PXD013003/83bc28059143c1d8___Katja_Exp3_Sample3_4.raw.-1.mgf"}, {"accession": "MS:1002850", "name": "Peak list file URI", "value": "ftp://ftp.pride.ebi.ac.uk/pride/data/archive/2019/11/PXD013003/83bc28059143c1d8___Katja_Exp3_Sample3_4_R.raw.-1.mgf"}, {"accession": "MS:1002850", "name": "Peak list file URI", "value": "ftp://ftp.pride.ebi.ac.uk/pride/data/archive/2019/11/PXD013003/83bc28059143c1d8___Katja_Exp3_Sample3_5.raw.-1.mgf"}, {"accession": "MS:1002850", "name": "Peak list file URI", "value": "ftp://ftp.pride.ebi.ac.uk/pride/data/archive/2019/11/PXD013003/83bc28059143c1d8___Katja_Exp3_Sample3_5_R.raw.-1.mgf"}, {"accession": "MS:1002850", "name": "Peak list file URI", "value": "ftp://ftp.pride.ebi.ac.uk/pride/data/archive/2019/11/PXD013003/83bc28059143c1d8___Katja_Exp3_Sample3_6.raw.-1.mgf"}, {"accession": "MS:1002850", "name": "Peak list file URI", "value": "ftp://ftp.pride.ebi.ac.uk/pride/data/archive/2019/11/PXD013003/83bc28059143c1d8___Katja_Exp3_Sample3_6_R.raw.-1.mgf"}, {"accession": "MS:1002850", "name": "Peak list file URI", "value": "ftp://ftp.pride.ebi.ac.uk/pride/data/archive/2019/11/PXD013003/83bc28059143c1d8___Katja_Exp3_Sample3_7.raw.-1.mgf"}, {"accession": "MS:1002850", "name": "Peak list file URI", "value": "ftp://ftp.pride.ebi.ac.uk/pride/data/archive/2019/11/PXD013003/83bc28059143c1d8___Katja_Exp3_Sample3_7_R.raw.-1.mgf"}, {"accession": "MS:1002850", "name": "Peak list file URI", "value": "ftp://ftp.pride.ebi.ac.uk/pride/data/archive/2019/11/PXD013003/83bc28059143c1d8___Katja_Exp3_Sample3_8.raw.-1.mgf"}, {"accession": "MS:1002850", "name": "Peak list file URI", "value": "ftp://ftp.pride.ebi.ac.uk/pride/data/archive/2019/11/PXD013003/83bc28059143c1d8___Katja_Exp3_Sample3_8_R.raw.-1.mgf"}, {"accession": "MS:1002850", "name": "Peak list file URI", "value": "ftp://ftp.pride.ebi.ac.uk/pride/data/archive/2019/11/PXD013003/83bc28059143c1d8___Katja_Exp4Sample4_6_R.raw.-1.mgf"}, {"accession": "MS:1002850", "name": "Peak list file URI", "value": "ftp://ftp.pride.ebi.ac.uk/pride/data/archive/2019/11/PXD013003/83bc28059143c1d8___Katja_Exp4_Sample4_1.raw.-1.mgf"}, {"accession": "MS:1002850", "name": "Peak list file URI", "value": "ftp://ftp.pride.ebi.ac.uk/pride/data/archive/2019/11/PXD013003/83bc28059143c1d8___Katja_Exp4_Sample4_1_R.raw.-1.mgf"}, {"accession": "MS:1002850", "name": "Peak list file URI", "value": "ftp://ftp.pride.ebi.ac.uk/pride/data/archive/2019/11/PXD013003/83bc28059143c1d8___Katja_Exp4_Sample4_2.raw.-1.mgf"}, {"accession": "MS:1002850", "name": "Peak list file URI", "value": "ftp://ftp.pride.ebi.ac.uk/pride/data/archive/2019/11/PXD013003/83bc28059143c1d8___Katja_Exp4_Sample4_2_R.raw.-1.mgf"}, {"accession": "MS:1002850", "name": "Peak list file URI", "value": "ftp://ftp.pride.ebi.ac.uk/pride/data/archive/2019/11/PXD013003/83bc28059143c1d8___Katja_Exp4_Sample4_3.raw.-1.mgf"}, {"accession": "MS:1002850", "name": "Peak list file URI", "value": "ftp://ftp.pride.ebi.ac.uk/pride/data/archive/2019/11/PXD013003/83bc28059143c1d8___Katja_Exp4_Sample4_3_R.raw.-1.mgf"}, {"accession": "MS:1002850", "name": "Peak list file URI", "value": "ftp://ftp.pride.ebi.ac.uk/pride/data/archive/2019/11/PXD013003/83bc28059143c1d8___Katja_Exp4_Sample4_4.raw.-1.mgf"}, {"accession": "MS:1002850", "name": "Peak list file URI", "value": "ftp://ftp.pride.ebi.ac.uk/pride/data/archive/2019/11/PXD013003/83bc28059143c1d8___Katja_Exp4_Sample4_4_R.raw.-1.mgf"}, {"accession": "MS:1002850", "name": "Peak list file URI", "value": "ftp://ftp.pride.ebi.ac.uk/pride/data/archive/2019/11/PXD013003/83bc28059143c1d8___Katja_Exp4_Sample4_5.raw.-1.mgf"}, {"accession": "MS:1002850", "name": "Peak list file URI", "value": "ftp://ftp.pride.ebi.ac.uk/pride/data/archive/2019/11/PXD013003/83bc28059143c1d8___Katja_Exp4_Sample4_5_R.raw.-1.mgf"}, {"accession": "MS:1002850", "name": "Peak list file URI", "value": "ftp://ftp.pride.ebi.ac.uk/pride/data/archive/2019/11/PXD013003/83bc28059143c1d8___Katja_Exp4_Sample4_6.raw.-1.mgf"}, {"accession": "MS:1002850", "name": "Peak list file URI", "value": "ftp://ftp.pride.ebi.ac.uk/pride/data/archive/2019/11/PXD013003/83bc28059143c1d8___Katja_Exp4_Sample4_7.raw.-1.mgf"}, {"accession": "MS:1002850", "name": "Peak list file URI", "value": "ftp://ftp.pride.ebi.ac.uk/pride/data/archive/2019/11/PXD013003/83bc28059143c1d8___Katja_Exp4_Sample4_7_R.raw.-1.mgf"}, {"accession": "MS:1002850", "name": "Peak list file URI", "value": "ftp://ftp.pride.ebi.ac.uk/pride/data/archive/2019/11/PXD013003/83bc28059143c1d8___Katja_Exp4_Sample4_8.raw.-1.mgf"}, {"accession": "MS:1002850", "name": "Peak list file URI", "value": "ftp://ftp.pride.ebi.ac.uk/pride/data/archive/2019/11/PXD013003/83bc28059143c1d8___Katja_Exp4_Sample4_8_R.raw.-1.mgf"}, {"accession": "MS:1002850", "name": "Peak list file URI", "value": "ftp://ftp.pride.ebi.ac.uk/pride/data/archive/2019/11/PXD013003/be9a6215ac64a683___Katja_Exp5_Sample5_1a.raw.-1.mgf"}, {"accession": "MS:1002850", "name": "Peak list file URI", "value": "ftp://ftp.pride.ebi.ac.uk/pride/data/archive/2019/11/PXD013003/be9a6215ac64a683___Katja_Exp5_Sample5_1a_R.raw.-1.mgf"}, {"accession": "MS:1002850", "name": "Peak list file URI", "value": "ftp://ftp.pride.ebi.ac.uk/pride/data/archive/2019/11/PXD013003/be9a6215ac64a683___Katja_Exp5_Sample5_1b.raw.-1.mgf"}, {"accession": "MS:1002850", "name": "Peak list file URI", "value": "ftp://ftp.pride.ebi.ac.uk/pride/data/archive/2019/11/PXD013003/be9a6215ac64a683___Katja_Exp5_Sample5_1b_R.raw.-1.mgf"}, {"accession": "MS:1002850", "name": "Peak list file URI", "value": "ftp://ftp.pride.ebi.ac.uk/pride/data/archive/2019/11/PXD013003/be9a6215ac64a683___Katja_Exp5_Sample5_2a.raw.-1.mgf"}, {"accession": "MS:1002850", "name": "Peak list file URI", "value": "ftp://ftp.pride.ebi.ac.uk/pride/data/archive/2019/11/PXD013003/be9a6215ac64a683___Katja_Exp5_Sample5_2a_R.raw.-1.mgf"}, {"accession": "MS:1002850", "name": "Peak list file URI", "value": "ftp://ftp.pride.ebi.ac.uk/pride/data/archive/2019/11/PXD013003/be9a6215ac64a683___Katja_Exp5_Sample5_2b.raw.-1.mgf"}, {"accession": "MS:1002850", "name": "Peak list file URI", "value": "ftp://ftp.pride.ebi.ac.uk/pride/data/archive/2019/11/PXD013003/be9a6215ac64a683___Katja_Exp5_Sample5_2b_R.raw.-1.mgf"}, {"accession": "MS:1002850", "name": "Peak list file URI", "value": "ftp://ftp.pride.ebi.ac.uk/pride/data/archive/2019/11/PXD013003/be9a6215ac64a683___Katja_Exp5_Sample5_3a.raw.-1.mgf"}, {"accession": "MS:1002850", "name": "Peak list file URI", "value": "ftp://ftp.pride.ebi.ac.uk/pride/data/archive/2019/11/PXD013003/be9a6215ac64a683___Katja_Exp5_Sample5_3a_R.raw.-1.mgf"}, {"accession": "MS:1002850", "name": "Peak list file URI", "value": "ftp://ftp.pride.ebi.ac.uk/pride/data/archive/2019/11/PXD013003/be9a6215ac64a683___Katja_Exp5_Sample5_3b.raw.-1.mgf"}, {"accession": "MS:1002850", "name": "Peak list file URI", "value": "ftp://ftp.pride.ebi.ac.uk/pride/data/archive/2019/11/PXD013003/be9a6215ac64a683___Katja_Exp5_Sample5_3b_R.raw.-1.mgf"}, {"accession": "MS:1002850", "name": "Peak list file URI", "value": "ftp://ftp.pride.ebi.ac.uk/pride/data/archive/2019/11/PXD013003/be9a6215ac64a683___Katja_Exp5_Sample5_4a.raw.-1.mgf"}, {"accession": "MS:1002850", "name": "Peak list file URI", "value": "ftp://ftp.pride.ebi.ac.uk/pride/data/archive/2019/11/PXD013003/be9a6215ac64a683___Katja_Exp5_Sample5_4a_R.raw.-1.mgf"}, {"accession": "MS:1002850", "name": "Peak list file URI", "value": "ftp://ftp.pride.ebi.ac.uk/pride/data/archive/2019/11/PXD013003/be9a6215ac64a683___Katja_Exp5_Sample5_4b.raw.-1.mgf"}, {"accession": "MS:1002850", "name": "Peak list file URI", "value": "ftp://ftp.pride.ebi.ac.uk/pride/data/archive/2019/11/PXD013003/be9a6215ac64a683___Katja_Exp5_Sample5_4b_R.raw.-1.mgf"}, {"accession": "MS:1002850", "name": "Peak list file URI", "value": "ftp://ftp.pride.ebi.ac.uk/pride/data/archive/2019/11/PXD013003/be9a6215ac64a683___Katja_Exp5_Sample5_5a.raw.-1.mgf"}, {"accession": "MS:1002850", "name": "Peak list file URI", "value": "ftp://ftp.pride.ebi.ac.uk/pride/data/archive/2019/11/PXD013003/be9a6215ac64a683___Katja_Exp5_Sample5_5a_R.raw.-1.mgf"}, {"accession": "MS:1002850", "name": "Peak list file URI", "value": "ftp://ftp.pride.ebi.ac.uk/pride/data/archive/2019/11/PXD013003/be9a6215ac64a683___Katja_Exp5_Sample5_5b.raw.-1.mgf"}, {"accession": "MS:1002850", "name": "Peak list file URI", "value": "ftp://ftp.pride.ebi.ac.uk/pride/data/archive/2019/11/PXD013003/be9a6215ac64a683___Katja_Exp5_Sample5_5b_R.raw.-1.mgf"}, {"accession": "MS:1002850", "name": "Peak list file URI", "value": "ftp://ftp.pride.ebi.ac.uk/pride/data/archive/2019/11/PXD013003/be9a6215ac64a683___Katja_Exp5_Sample5_6a.raw.-1.mgf"}, {"accession": "MS:1002850", "name": "Peak list file URI", "value": "ftp://ftp.pride.ebi.ac.uk/pride/data/archive/2019/11/PXD013003/be9a6215ac64a683___Katja_Exp5_Sample5_6a_R.raw.-1.mgf"}, {"accession": "MS:1002850", "name": "Peak list file URI", "value": "ftp://ftp.pride.ebi.ac.uk/pride/data/archive/2019/11/PXD013003/be9a6215ac64a683___Katja_Exp5_Sample5_6b.raw.-1.mgf"}, {"accession": "MS:1002850", "name": "Peak list file URI", "value": "ftp://ftp.pride.ebi.ac.uk/pride/data/archive/2019/11/PXD013003/be9a6215ac64a683___Katja_Exp5_Sample5_6b_R.raw.-1.mgf"}, {"accession": "MS:1002850", "name": "Peak list file URI", "value": "ftp://ftp.pride.ebi.ac.uk/pride/data/archive/2019/11/PXD013003/be9a6215ac64a683___Katja_Exp5_Sample5_7a.raw.-1.mgf"}, {"accession": "MS:1002850", "name": "Peak list file URI", "value": "ftp://ftp.pride.ebi.ac.uk/pride/data/archive/2019/11/PXD013003/be9a6215ac64a683___Katja_Exp5_Sample5_7a_R.raw.-1.mgf"}, {"accession": "MS:1002850", "name": "Peak list file URI", "value": "ftp://ftp.pride.ebi.ac.uk/pride/data/archive/2019/11/PXD013003/be9a6215ac64a683___Katja_Exp5_Sample5_7b.raw.-1.mgf"}, {"accession": "MS:1002850", "name": "Peak list file URI", "value": "ftp://ftp.pride.ebi.ac.uk/pride/data/archive/2019/11/PXD013003/be9a6215ac64a683___Katja_Exp5_Sample5_7b_R.raw.-1.mgf"}, {"accession": "MS:1002850", "name": "Peak list file URI", "value": "ftp://ftp.pride.ebi.ac.uk/pride/data/archive/2019/11/PXD013003/be9a6215ac64a683___Katja_Exp5_Sample5_8a.raw.-1.mgf"}, {"accession": "MS:1002850", "name": "Peak list file URI", "value": "ftp://ftp.pride.ebi.ac.uk/pride/data/archive/2019/11/PXD013003/be9a6215ac64a683___Katja_Exp5_Sample5_8a_R.raw.-1.mgf"}, {"accession": "MS:1002850", "name": "Peak list file URI", "value": "ftp://ftp.pride.ebi.ac.uk/pride/data/archive/2019/11/PXD013003/be9a6215ac64a683___Katja_Exp5_Sample5_8b.raw.-1.mgf"}, {"accession": "MS:1002850", "name": "Peak list file URI", "value": "ftp://ftp.pride.ebi.ac.uk/pride/data/archive/2019/11/PXD013003/be9a6215ac64a683___Katja_Exp5_Sample5_8b_R.raw.-1.mgf"}, {"accession": "MS:1002846", "name": "Associated raw file URI", "value": "ftp://ftp.pride.ebi.ac.uk/pride/data/archive/2019/11/PXD013003/Katja_Exp3_Sample3_1.raw"}, {"accession": "MS:1002846", "name": "Associated raw file URI", "value": "ftp://ftp.pride.ebi.ac.uk/pride/data/archive/2019/11/PXD013003/Katja_Exp3_Sample3_1_R.raw"}, {"accession": "MS:1002846", "name": "Associated raw file URI", "value": "ftp://ftp.pride.ebi.ac.uk/pride/data/archive/2019/11/PXD013003/Katja_Exp3_Sample3_2.raw"}, {"accession": "MS:1002846", "name": "Associated raw file URI", "value": "ftp://ftp.pride.ebi.ac.uk/pride/data/archive/2019/11/PXD013003/Katja_Exp3_Sample3_2_R.raw"}, {"accession": "MS:1002846", "name": "Associated raw file URI", "value": "ftp://ftp.pride.ebi.ac.uk/pride/data/archive/2019/11/PXD013003/Katja_Exp3_Sample3_3.raw"}, {"accession": "MS:1002846", "name": "Associated raw file URI", "value": "ftp://ftp.pride.ebi.ac.uk/pride/data/archive/2019/11/PXD013003/Katja_Exp3_Sample3_3_R.raw"}, {"accession": "MS:1002846", "name": "Associated raw file URI", "value": "ftp://ftp.pride.ebi.ac.uk/pride/data/archive/2019/11/PXD013003/Katja_Exp3_Sample3_4.raw"}, {"accession": "MS:1002846", "name": "Associated raw file URI", "value": "ftp://ftp.pride.ebi.ac.uk/pride/data/archive/2019/11/PXD013003/Katja_Exp3_Sample3_4_R.raw"}, {"accession": "MS:1002846", "name": "Associated raw file URI", "value": "ftp://ftp.pride.ebi.ac.uk/pride/data/archive/2019/11/PXD013003/Katja_Exp3_Sample3_5.raw"}, {"accession": "MS:1002846", "name": "Associated raw file URI", "value": "ftp://ftp.pride.ebi.ac.uk/pride/data/archive/2019/11/PXD013003/Katja_Exp3_Sample3_5_R.raw"}, {"accession": "MS:1002846", "name": "Associated raw file URI", "value": "ftp://ftp.pride.ebi.ac.uk/pride/data/archive/2019/11/PXD013003/Katja_Exp3_Sample3_6.raw"}, {"accession": "MS:1002846", "name": "Associated raw file URI", "value": "ftp://ftp.pride.ebi.ac.uk/pride/data/archive/2019/11/PXD013003/Katja_Exp3_Sample3_6_R.raw"}, {"accession": "MS:1002846", "name": "Associated raw file URI", "value": "ftp://ftp.pride.ebi.ac.uk/pride/data/archive/2019/11/PXD013003/Katja_Exp3_Sample3_7.raw"}, {"accession": "MS:1002846", "name": "Associated raw file URI", "value": "ftp://ftp.pride.ebi.ac.uk/pride/data/archive/2019/11/PXD013003/Katja_Exp3_Sample3_7_R.raw"}, {"accession": "MS:1002846", "name": "Associated raw file URI", "value": "ftp://ftp.pride.ebi.ac.uk/pride/data/archive/2019/11/PXD013003/Katja_Exp3_Sample3_8.raw"}, {"accession": "MS:1002846", "name": "Associated raw file URI", "value": "ftp://ftp.pride.ebi.ac.uk/pride/data/archive/2019/11/PXD013003/Katja_Exp3_Sample3_8_R.raw"}, {"accession": "MS:1002846", "name": "Associated raw file URI", "value": "ftp://ftp.pride.ebi.ac.uk/pride/data/archive/2019/11/PXD013003/Katja_Exp4Sample4_6_R.raw"}, {"accession": "MS:1002846", "name": "Associated raw file URI", "value": "ftp://ftp.pride.ebi.ac.uk/pride/data/archive/2019/11/PXD013003/Katja_Exp4_Sample4_1.raw"}, {"accession": "MS:1002846", "name": "Associated raw file URI", "value": "ftp://ftp.pride.ebi.ac.uk/pride/data/archive/2019/11/PXD013003/Katja_Exp4_Sample4_1_R.raw"}, {"accession": "MS:1002846", "name": "Associated raw file URI", "value": "ftp://ftp.pride.ebi.ac.uk/pride/data/archive/2019/11/PXD013003/Katja_Exp4_Sample4_2.raw"}, {"accession": "MS:1002846", "name": "Associated raw file URI", "value": "ftp://ftp.pride.ebi.ac.uk/pride/data/archive/2019/11/PXD013003/Katja_Exp4_Sample4_2_R.raw"}, {"accession": "MS:1002846", "name": "Associated raw file URI", "value": "ftp://ftp.pride.ebi.ac.uk/pride/data/archive/2019/11/PXD013003/Katja_Exp4_Sample4_3.raw"}, {"accession": "MS:1002846", "name": "Associated raw file URI", "value": "ftp://ftp.pride.ebi.ac.uk/pride/data/archive/2019/11/PXD013003/Katja_Exp4_Sample4_3_R.raw"}, {"accession": "MS:1002846", "name": "Associated raw file URI", "value": "ftp://ftp.pride.ebi.ac.uk/pride/data/archive/2019/11/PXD013003/Katja_Exp4_Sample4_4.raw"}, {"accession": "MS:1002846", "name": "Associated raw file URI", "value": "ftp://ftp.pride.ebi.ac.uk/pride/data/archive/2019/11/PXD013003/Katja_Exp4_Sample4_4_R.raw"}, {"accession": "MS:1002846", "name": "Associated raw file URI", "value": "ftp://ftp.pride.ebi.ac.uk/pride/data/archive/2019/11/PXD013003/Katja_Exp4_Sample4_5.raw"}, {"accession": "MS:1002846", "name": "Associated raw file URI", "value": "ftp://ftp.pride.ebi.ac.uk/pride/data/archive/2019/11/PXD013003/Katja_Exp4_Sample4_5_R.raw"}, {"accession": "MS:1002846", "name": "Associated raw file URI", "value": "ftp://ftp.pride.ebi.ac.uk/pride/data/archive/2019/11/PXD013003/Katja_Exp4_Sample4_6.raw"}, {"accession": "MS:1002846", "name": "Associated raw file URI", "value": "ftp://ftp.pride.ebi.ac.uk/pride/data/archive/2019/11/PXD013003/Katja_Exp4_Sample4_7.raw"}, {"accession": "MS:1002846", "name": "Associated raw file URI", "value": "ftp://ftp.pride.ebi.ac.uk/pride/data/archive/2019/11/PXD013003/Katja_Exp4_Sample4_7_R.raw"}, {"accession": "MS:1002846", "name": "Associated raw file URI", "value": "ftp://ftp.pride.ebi.ac.uk/pride/data/archive/2019/11/PXD013003/Katja_Exp4_Sample4_8.raw"}, {"accession": "MS:1002846", "name": "Associated raw file URI", "value": "ftp://ftp.pride.ebi.ac.uk/pride/data/archive/2019/11/PXD013003/Katja_Exp4_Sample4_8_R.raw"}, {"accession": "MS:1002846", "name": "Associated raw file URI", "value": "ftp://ftp.pride.ebi.ac.uk/pride/data/archive/2019/11/PXD013003/Katja_Exp5_Sample5_1a.raw"}, {"accession": "MS:1002846", "name": "Associated raw file URI", "value": "ftp://ftp.pride.ebi.ac.uk/pride/data/archive/2019/11/PXD013003/Katja_Exp5_Sample5_1a_R.raw"}, {"accession": "MS:1002846", "name": "Associated raw file URI", "value": "ftp://ftp.pride.ebi.ac.uk/pride/data/archive/2019/11/PXD013003/Katja_Exp5_Sample5_1b.raw"}, {"accession": "MS:1002846", "name": "Associated raw file URI", "value": "ftp://ftp.pride.ebi.ac.uk/pride/data/archive/2019/11/PXD013003/Katja_Exp5_Sample5_1b_R.raw"}, {"accession": "MS:1002846", "name": "Associated raw file URI", "value": "ftp://ftp.pride.ebi.ac.uk/pride/data/archive/2019/11/PXD013003/Katja_Exp5_Sample5_2a.raw"}, {"accession": "MS:1002846", "name": "Associated raw file URI", "value": "ftp://ftp.pride.ebi.ac.uk/pride/data/archive/2019/11/PXD013003/Katja_Exp5_Sample5_2a_R.raw"}, {"accession": "MS:1002846", "name": "Associated raw file URI", "value": "ftp://ftp.pride.ebi.ac.uk/pride/data/archive/2019/11/PXD013003/Katja_Exp5_Sample5_2b.raw"}, {"accession": "MS:1002846", "name": "Associated raw file URI", "value": "ftp://ftp.pride.ebi.ac.uk/pride/data/archive/2019/11/PXD013003/Katja_Exp5_Sample5_2b_R.raw"}, {"accession": "MS:1002846", "name": "Associated raw file URI", "value": "ftp://ftp.pride.ebi.ac.uk/pride/data/archive/2019/11/PXD013003/Katja_Exp5_Sample5_3a.raw"}, {"accession": "MS:1002846", "name": "Associated raw file URI", "value": "ftp://ftp.pride.ebi.ac.uk/pride/data/archive/2019/11/PXD013003/Katja_Exp5_Sample5_3a_R.raw"}, {"accession": "MS:1002846", "name": "Associated raw file URI", "value": "ftp://ftp.pride.ebi.ac.uk/pride/data/archive/2019/11/PXD013003/Katja_Exp5_Sample5_3b.raw"}, {"accession": "MS:1002846", "name": "Associated raw file URI", "value": "ftp://ftp.pride.ebi.ac.uk/pride/data/archive/2019/11/PXD013003/Katja_Exp5_Sample5_3b_R.raw"}, {"accession": "MS:1002846", "name": "Associated raw file URI", "value": "ftp://ftp.pride.ebi.ac.uk/pride/data/archive/2019/11/PXD013003/Katja_Exp5_Sample5_4a.raw"}, {"accession": "MS:1002846", "name": "Associated raw file URI", "value": "ftp://ftp.pride.ebi.ac.uk/pride/data/archive/2019/11/PXD013003/Katja_Exp5_Sample5_4a_R.raw"}, {"accession": "MS:1002846", "name": "Associated raw file URI", "value": "ftp://ftp.pride.ebi.ac.uk/pride/data/archive/2019/11/PXD013003/Katja_Exp5_Sample5_4b.raw"}, {"accession": "MS:1002846", "name": "Associated raw file URI", "value": "ftp://ftp.pride.ebi.ac.uk/pride/data/archive/2019/11/PXD013003/Katja_Exp5_Sample5_4b_R.raw"}, {"accession": "MS:1002846", "name": "Associated raw file URI", "value": "ftp://ftp.pride.ebi.ac.uk/pride/data/archive/2019/11/PXD013003/Katja_Exp5_Sample5_5a.raw"}, {"accession": "MS:1002846", "name": "Associated raw file URI", "value": "ftp://ftp.pride.ebi.ac.uk/pride/data/archive/2019/11/PXD013003/Katja_Exp5_Sample5_5a_R.raw"}, {"accession": "MS:1002846", "name": "Associated raw file URI", "value": "ftp://ftp.pride.ebi.ac.uk/pride/data/archive/2019/11/PXD013003/Katja_Exp5_Sample5_5b.raw"}, {"accession": "MS:1002846", "name": "Associated raw file URI", "value": "ftp://ftp.pride.ebi.ac.uk/pride/data/archive/2019/11/PXD013003/Katja_Exp5_Sample5_5b_R.raw"}, {"accession": "MS:1002846", "name": "Associated raw file URI", "value": "ftp://ftp.pride.ebi.ac.uk/pride/data/archive/2019/11/PXD013003/Katja_Exp5_Sample5_6a.raw"}, {"accession": "MS:1002846", "name": "Associated raw file URI", "value": "ftp://ftp.pride.ebi.ac.uk/pride/data/archive/2019/11/PXD013003/Katja_Exp5_Sample5_6a_R.raw"}, {"accession": "MS:1002846", "name": "Associated raw file URI", "value": "ftp://ftp.pride.ebi.ac.uk/pride/data/archive/2019/11/PXD013003/Katja_Exp5_Sample5_6b.raw"}, {"accession": "MS:1002846", "name": "Associated raw file URI", "value": "ftp://ftp.pride.ebi.ac.uk/pride/data/archive/2019/11/PXD013003/Katja_Exp5_Sample5_6b_R.raw"}, {"accession": "MS:1002846", "name": "Associated raw file URI", "value": "ftp://ftp.pride.ebi.ac.uk/pride/data/archive/2019/11/PXD013003/Katja_Exp5_Sample5_7a.raw"}, {"accession": "MS:1002846", "name": "Associated raw file URI", "value": "ftp://ftp.pride.ebi.ac.uk/pride/data/archive/2019/11/PXD013003/Katja_Exp5_Sample5_7a_R.raw"}, {"accession": "MS:1002846", "name": "Associated raw file URI", "value": "ftp://ftp.pride.ebi.ac.uk/pride/data/archive/2019/11/PXD013003/Katja_Exp5_Sample5_7b.raw"}, {"accession": "MS:1002846", "name": "Associated raw file URI", "value": "ftp://ftp.pride.ebi.ac.uk/pride/data/archive/2019/11/PXD013003/Katja_Exp5_Sample5_7b_R.raw"}, {"accession": "MS:1002846", "name": "Associated raw file URI", "value": "ftp://ftp.pride.ebi.ac.uk/pride/data/archive/2019/11/PXD013003/Katja_Exp5_Sample5_8a.raw"}, {"accession": "MS:1002846", "name": "Associated raw file URI", "value": "ftp://ftp.pride.ebi.ac.uk/pride/data/archive/2019/11/PXD013003/Katja_Exp5_Sample5_8a_R.raw"}, {"accession": "MS:1002846", "name": "Associated raw file URI", "value": "ftp://ftp.pride.ebi.ac.uk/pride/data/archive/2019/11/PXD013003/Katja_Exp5_Sample5_8b.raw"}, {"accession": "MS:1002846", "name": "Associated raw file URI", "value": "ftp://ftp.pride.ebi.ac.uk/pride/data/archive/2019/11/PXD013003/Katja_Exp5_Sample5_8b_R.raw"}, {"accession": "MS:1002846", "name": "Associated raw file URI", "value": "ftp://ftp.pride.ebi.ac.uk/pride/data/archive/2019/11/PXD013003/Katja_Exp6_Sample6_1a.raw"}, {"accession": "MS:1002846", "name": "Associated raw file URI", "value": "ftp://ftp.pride.ebi.ac.uk/pride/data/archive/2019/11/PXD013003/Katja_Exp6_Sample6_1a_R.raw"}, {"accession": "MS:1002846", "name": "Associated raw file URI", "value": "ftp://ftp.pride.ebi.ac.uk/pride/data/archive/2019/11/PXD013003/Katja_Exp6_Sample6_1b.raw"}, {"accession": "MS:1002846", "name": "Associated raw file URI", "value": "ftp://ftp.pride.ebi.ac.uk/pride/data/archive/2019/11/PXD013003/Katja_Exp6_Sample6_1b_R.raw"}, {"accession": "MS:1002846", "name": "Associated raw file URI", "value": "ftp://ftp.pride.ebi.ac.uk/pride/data/archive/2019/11/PXD013003/Katja_Exp6_Sample6_2a.raw"}, {"accession": "MS:1002846", "name": "Associated raw file URI", "value": "ftp://ftp.pride.ebi.ac.uk/pride/data/archive/2019/11/PXD013003/Katja_Exp6_Sample6_2a_R.raw"}, {"accession": "MS:1002846", "name": "Associated raw file URI", "value": "ftp://ftp.pride.ebi.ac.uk/pride/data/archive/2019/11/PXD013003/Katja_Exp6_Sample6_2b.raw"}, {"accession": "MS:1002846", "name": "Associated raw file URI", "value": "ftp://ftp.pride.ebi.ac.uk/pride/data/archive/2019/11/PXD013003/Katja_Exp6_Sample6_2b_R.raw"}, {"accession": "MS:1002846", "name": "Associated raw file URI", "value": "ftp://ftp.pride.ebi.ac.uk/pride/data/archive/2019/11/PXD013003/Katja_Exp6_Sample6_3a.raw"}, {"accession": "MS:1002846", "name": "Associated raw file URI", "value": "ftp://ftp.pride.ebi.ac.uk/pride/data/archive/2019/11/PXD013003/Katja_Exp6_Sample6_3a_R.raw"}, {"accession": "MS:1002846", "name": "Associated raw file URI", "value": "ftp://ftp.pride.ebi.ac.uk/pride/data/archive/2019/11/PXD013003/Katja_Exp6_Sample6_3b.raw"}, {"accession": "MS:1002846", "name": "Associated raw file URI", "value": "ftp://ftp.pride.ebi.ac.uk/pride/data/archive/2019/11/PXD013003/Katja_Exp6_Sample6_3b_R.raw"}, {"accession": "MS:1002846", "name": "Associated raw file URI", "value": "ftp://ftp.pride.ebi.ac.uk/pride/data/archive/2019/11/PXD013003/Katja_Exp6_Sample6_4a.raw"}, {"accession": "MS:1002846", "name": "Associated raw file URI", "value": "ftp://ftp.pride.ebi.ac.uk/pride/data/archive/2019/11/PXD013003/Katja_Exp6_Sample6_4a_R.raw"}, {"accession": "MS:1002846", "name": "Associated raw file URI", "value": "ftp://ftp.pride.ebi.ac.uk/pride/data/archive/2019/11/PXD013003/Katja_Exp6_Sample6_4b.raw"}, {"accession": "MS:1002846", "name": "Associated raw file URI", "value": "ftp://ftp.pride.ebi.ac.uk/pride/data/archive/2019/11/PXD013003/Katja_Exp6_Sample6_4b_R.raw"}, {"accession": "MS:1002846", "name": "Associated raw file URI", "value": "ftp://ftp.pride.ebi.ac.uk/pride/data/archive/2019/11/PXD013003/Katja_Exp6_Sample6_5a.raw"}, {"accession": "MS:1002846", "name": "Associated raw file URI", "value": "ftp://ftp.pride.ebi.ac.uk/pride/data/archive/2019/11/PXD013003/Katja_Exp6_Sample6_5a_R.raw"}, {"accession": "MS:1002846", "name": "Associated raw file URI", "value": "ftp://ftp.pride.ebi.ac.uk/pride/data/archive/2019/11/PXD013003/Katja_Exp6_Sample6_5b.raw"}, {"accession": "MS:1002846", "name": "Associated raw file URI", "value": "ftp://ftp.pride.ebi.ac.uk/pride/data/archive/2019/11/PXD013003/Katja_Exp6_Sample6_5b_R.raw"}, {"accession": "MS:1002846", "name": "Associated raw file URI", "value": "ftp://ftp.pride.ebi.ac.uk/pride/data/archive/2019/11/PXD013003/Katja_Exp6_Sample6_6a.raw"}, {"accession": "MS:1002846", "name": "Associated raw file URI", "value": "ftp://ftp.pride.ebi.ac.uk/pride/data/archive/2019/11/PXD013003/Katja_Exp6_Sample6_6a_R.raw"}, {"accession": "MS:1002846", "name": "Associated raw file URI", "value": "ftp://ftp.pride.ebi.ac.uk/pride/data/archive/2019/11/PXD013003/Katja_Exp6_Sample6_6b.raw"}, {"accession": "MS:1002846", "name": "Associated raw file URI", "value": "ftp://ftp.pride.ebi.ac.uk/pride/data/archive/2019/11/PXD013003/Katja_Exp6_Sample6_6b_R.raw"}, {"accession": "MS:1002846", "name": "Associated raw file URI", "value": "ftp://ftp.pride.ebi.ac.uk/pride/data/archive/2019/11/PXD013003/Katja_Exp6_Sample6_7a.raw"}, {"accession": "MS:1002846", "name": "Associated raw file URI", "value": "ftp://ftp.pride.ebi.ac.uk/pride/data/archive/2019/11/PXD013003/Katja_Exp6_Sample6_7a_R.raw"}, {"accession": "MS:1002846", "name": "Associated raw file URI", "value": "ftp://ftp.pride.ebi.ac.uk/pride/data/archive/2019/11/PXD013003/Katja_Exp6_Sample6_7b.raw"}, {"accession": "MS:1002846", "name": "Associated raw file URI", "value": "ftp://ftp.pride.ebi.ac.uk/pride/data/archive/2019/11/PXD013003/Katja_Exp6_Sample6_7b_R.raw"}, {"accession": "MS:1002846", "name": "Associated raw file URI", "value": "ftp://ftp.pride.ebi.ac.uk/pride/data/archive/2019/11/PXD013003/Katja_Exp6_Sample6_8a.raw"}, {"accession": "MS:1002846", "name": "Associated raw file URI", "value": "ftp://ftp.pride.ebi.ac.uk/pride/data/archive/2019/11/PXD013003/Katja_Exp6_Sample6_8a_R.raw"}, {"accession": "MS:1002846", "name": "Associated raw file URI", "value": "ftp://ftp.pride.ebi.ac.uk/pride/data/archive/2019/11/PXD013003/Katja_Exp6_Sample6_8b.raw"}, {"accession": "MS:1002846", "name": "Associated raw file URI", "value": "ftp://ftp.pride.ebi.ac.uk/pride/data/archive/2019/11/PXD013003/Katja_Exp6_Sample6_8b_R.raw"}, {"accession": "MS:1002846", "name": "Associated raw file URI", "value": "ftp://ftp.pride.ebi.ac.uk/pride/data/archive/2019/11/PXD013003/QE1_Katja_Exp10_sample7A.raw"}, {"accession": "MS:1002846", "name": "Associated raw file URI", "value": "ftp://ftp.pride.ebi.ac.uk/pride/data/archive/2019/11/PXD013003/QE1_Katja_Exp10_sample7A_R.raw"}, {"accession": "MS:1002846", "name": "Associated raw file URI", "value": "ftp://ftp.pride.ebi.ac.uk/pride/data/archive/2019/11/PXD013003/QE1_Katja_Exp10_sample7B.raw"}, {"accession": "MS:1002846", "name": "Associated raw file URI", "value": "ftp://ftp.pride.ebi.ac.uk/pride/data/archive/2019/11/PXD013003/QE1_Katja_Exp10_sample7B_R.raw"}, {"accession": "MS:1002846", "name": "Associated raw file URI", "value": "ftp://ftp.pride.ebi.ac.uk/pride/data/archive/2019/11/PXD013003/QE1_Katja_Exp10_sample8A.raw"}, {"accession": "MS:1002846", "name": "Associated raw file URI", "value": "ftp://ftp.pride.ebi.ac.uk/pride/data/archive/2019/11/PXD013003/QE1_Katja_Exp10_sample8A_R.raw"}, {"accession": "MS:1002846", "name": "Associated raw file URI", "value": "ftp://ftp.pride.ebi.ac.uk/pride/data/archive/2019/11/PXD013003/QE1_Katja_Exp10_sample8B.raw"}, {"accession": "MS:1002846", "name": "Associated raw file URI", "value": "ftp://ftp.pride.ebi.ac.uk/pride/data/archive/2019/11/PXD013003/QE1_Katja_Exp10_sample8B_R.raw"}, {"accession": "MS:1002846", "name": "Associated raw file URI", "value": "ftp://ftp.pride.ebi.ac.uk/pride/data/archive/2019/11/PXD013003/QE1_Katja_Exp7_sample1A.raw"}, {"accession": "MS:1002846", "name": "Associated raw file URI", "value": "ftp://ftp.pride.ebi.ac.uk/pride/data/archive/2019/11/PXD013003/QE1_Katja_Exp7_sample1A_R.raw"}, {"accession": "MS:1002846", "name": "Associated raw file URI", "value": "ftp://ftp.pride.ebi.ac.uk/pride/data/archive/2019/11/PXD013003/QE1_Katja_Exp7_sample1B.raw"}, {"accession": "MS:1002846", "name": "Associated raw file URI", "value": "ftp://ftp.pride.ebi.ac.uk/pride/data/archive/2019/11/PXD013003/QE1_Katja_Exp7_sample1B_R.raw"}, {"accession": "MS:1002846", "name": "Associated raw file URI", "value": "ftp://ftp.pride.ebi.ac.uk/pride/data/archive/2019/11/PXD013003/QE1_Katja_Exp7_sample2A.raw"}, {"accession": "MS:1002846", "name": "Associated raw file URI", "value": "ftp://ftp.pride.ebi.ac.uk/pride/data/archive/2019/11/PXD013003/QE1_Katja_Exp7_sample2A_R.raw"}, {"accession": "MS:1002846", "name": "Associated raw file URI", "value": "ftp://ftp.pride.ebi.ac.uk/pride/data/archive/2019/11/PXD013003/QE1_Katja_Exp7_sample2B.raw"}, {"accession": "MS:1002846", "name": "Associated raw file URI", "value": "ftp://ftp.pride.ebi.ac.uk/pride/data/archive/2019/11/PXD013003/QE1_Katja_Exp7_sample2B_R.raw"}, {"accession": "MS:1002846", "name": "Associated raw file URI", "value": "ftp://ftp.pride.ebi.ac.uk/pride/data/archive/2019/11/PXD013003/QE1_Katja_Exp7_sample3A.raw"}, {"accession": "MS:1002846", "name": "Associated raw file URI", "value": "ftp://ftp.pride.ebi.ac.uk/pride/data/archive/2019/11/PXD013003/QE1_Katja_Exp7_sample3A_R.raw"}, {"accession": "MS:1002846", "name": "Associated raw file URI", "value": "ftp://ftp.pride.ebi.ac.uk/pride/data/archive/2019/11/PXD013003/QE1_Katja_Exp7_sample3B.raw"}, {"accession": "MS:1002846", "name": "Associated raw file URI", "value": "ftp://ftp.pride.ebi.ac.uk/pride/data/archive/2019/11/PXD013003/QE1_Katja_Exp7_sample3B_R.raw"}, {"accession": "MS:1002846", "name": "Associated raw file URI", "value": "ftp://ftp.pride.ebi.ac.uk/pride/data/archive/2019/11/PXD013003/QE1_Katja_Exp7_sample4A.raw"}, {"accession": "MS:1002846", "name": "Associated raw file URI", "value": "ftp://ftp.pride.ebi.ac.uk/pride/data/archive/2019/11/PXD013003/QE1_Katja_Exp7_sample4A_R.raw"}, {"accession": "MS:1002846", "name": "Associated raw file URI", "value": "ftp://ftp.pride.ebi.ac.uk/pride/data/archive/2019/11/PXD013003/QE1_Katja_Exp7_sample4B.raw"}, {"accession": "MS:1002846", "name": "Associated raw file URI", "value": "ftp://ftp.pride.ebi.ac.uk/pride/data/archive/2019/11/PXD013003/QE1_Katja_Exp7_sample4B_R.raw"}, {"accession": "MS:1002846", "name": "Associated raw file URI", "value": "ftp://ftp.pride.ebi.ac.uk/pride/data/archive/2019/11/PXD013003/QE1_Katja_Exp7_sample8A.raw"}, {"accession": "MS:1002846", "name": "Associated raw file URI", "value": "ftp://ftp.pride.ebi.ac.uk/pride/data/archive/2019/11/PXD013003/QE1_Katja_Exp7_sample8A_R.raw"}, {"accession": "MS:1002846", "name": "Associated raw file URI", "value": "ftp://ftp.pride.ebi.ac.uk/pride/data/archive/2019/11/PXD013003/QE1_Katja_Exp8_sample1A.raw"}, {"accession": "MS:1002846", "name": "Associated raw file URI", "value": "ftp://ftp.pride.ebi.ac.uk/pride/data/archive/2019/11/PXD013003/QE1_Katja_Exp8_sample1A_R.raw"}, {"accession": "MS:1002846", "name": "Associated raw file URI", "value": "ftp://ftp.pride.ebi.ac.uk/pride/data/archive/2019/11/PXD013003/QE1_Katja_Exp8_sample1B.raw"}, {"accession": "MS:1002846", "name": "Associated raw file URI", "value": "ftp://ftp.pride.ebi.ac.uk/pride/data/archive/2019/11/PXD013003/QE1_Katja_Exp8_sample1B_R.raw"}, {"accession": "MS:1002846", "name": "Associated raw file URI", "value": "ftp://ftp.pride.ebi.ac.uk/pride/data/archive/2019/11/PXD013003/QE1_Katja_Exp8_sample2A.raw"}, {"accession": "MS:1002846", "name": "Associated raw file URI", "value": "ftp://ftp.pride.ebi.ac.uk/pride/data/archive/2019/11/PXD013003/QE1_Katja_Exp8_sample2A_R.raw"}, {"accession": "MS:1002846", "name": "Associated raw file URI", "value": "ftp://ftp.pride.ebi.ac.uk/pride/data/archive/2019/11/PXD013003/QE1_Katja_Exp8_sample2B.raw"}, {"accession": "MS:1002846", "name": "Associated raw file URI", "value": "ftp://ftp.pride.ebi.ac.uk/pride/data/archive/2019/11/PXD013003/QE1_Katja_Exp8_sample2B_R.raw"}, {"accession": "MS:1002846", "name": "Associated raw file URI", "value": "ftp://ftp.pride.ebi.ac.uk/pride/data/archive/2019/11/PXD013003/QE1_Katja_Exp8_sample3A.raw"}, {"accession": "MS:1002846", "name": "Associated raw file URI", "value": "ftp://ftp.pride.ebi.ac.uk/pride/data/archive/2019/11/PXD013003/QE1_Katja_Exp8_sample3A_R.raw"}, {"accession": "MS:1002846", "name": "Associated raw file URI", "value": "ftp://ftp.pride.ebi.ac.uk/pride/data/archive/2019/11/PXD013003/QE1_Katja_Exp8_sample3B.raw"}, {"accession": "MS:1002846", "name": "Associated raw file URI", "value": "ftp://ftp.pride.ebi.ac.uk/pride/data/archive/2019/11/PXD013003/QE1_Katja_Exp8_sample3B_R.raw"}, {"accession": "MS:1002846", "name": "Associated raw file URI", "value": "ftp://ftp.pride.ebi.ac.uk/pride/data/archive/2019/11/PXD013003/QE1_Katja_Exp8_sample4A.raw"}, {"accession": "MS:1002846", "name": "Associated raw file URI", "value": "ftp://ftp.pride.ebi.ac.uk/pride/data/archive/2019/11/PXD013003/QE1_Katja_Exp8_sample4A_R.raw"}, {"accession": "MS:1002846", "name": "Associated raw file URI", "value": "ftp://ftp.pride.ebi.ac.uk/pride/data/archive/2019/11/PXD013003/QE1_Katja_Exp8_sample4B.raw"}, {"accession": "MS:1002846", "name": "Associated raw file URI", "value": "ftp://ftp.pride.ebi.ac.uk/pride/data/archive/2019/11/PXD013003/QE1_Katja_Exp8_sample4B_R.raw"}, {"accession": "MS:1002846", "name": "Associated raw file URI", "value": "ftp://ftp.pride.ebi.ac.uk/pride/data/archive/2019/11/PXD013003/QE1_Katja_Exp8_sample5A.raw"}, {"accession": "MS:1002846", "name": "Associated raw file URI", "value": "ftp://ftp.pride.ebi.ac.uk/pride/data/archive/2019/11/PXD013003/QE1_Katja_Exp8_sample5A_R.raw"}, {"accession": "MS:1002846", "name": "Associated raw file URI", "value": "ftp://ftp.pride.ebi.ac.uk/pride/data/archive/2019/11/PXD013003/QE1_Katja_Exp8_sample5B.raw"}, {"accession": "MS:1002846", "name": "Associated raw file URI", "value": "ftp://ftp.pride.ebi.ac.uk/pride/data/archive/2019/11/PXD013003/QE1_Katja_Exp8_sample5B_R.raw"}, {"accession": "MS:1002846", "name": "Associated raw file URI", "value": "ftp://ftp.pride.ebi.ac.uk/pride/data/archive/2019/11/PXD013003/QE1_Katja_Exp8_sample6A.raw"}, {"accession": "MS:1002846", "name": "Associated raw file URI", "value": "ftp://ftp.pride.ebi.ac.uk/pride/data/archive/2019/11/PXD013003/QE1_Katja_Exp8_sample6A_R.raw"}, {"accession": "MS:1002846", "name": "Associated raw file URI", "value": "ftp://ftp.pride.ebi.ac.uk/pride/data/archive/2019/11/PXD013003/QE1_Katja_Exp8_sample6B.raw"}, {"accession": "MS:1002846", "name": "Associated raw file URI", "value": "ftp://ftp.pride.ebi.ac.uk/pride/data/archive/2019/11/PXD013003/QE1_Katja_Exp8_sample6B_R.raw"}, {"accession": "MS:1002846", "name": "Associated raw file URI", "value": "ftp://ftp.pride.ebi.ac.uk/pride/data/archive/2019/11/PXD013003/QE1_Katja_Exp8_sample7A.raw"}, {"accession": "MS:1002846", "name": "Associated raw file URI", "value": "ftp://ftp.pride.ebi.ac.uk/pride/data/archive/2019/11/PXD013003/QE1_Katja_Exp8_sample7A_R.raw"}, {"accession": "MS:1002846", "name": "Associated raw file URI", "value": "ftp://ftp.pride.ebi.ac.uk/pride/data/archive/2019/11/PXD013003/QE1_Katja_Exp8_sample7B_171116030750.raw"}, {"accession": "MS:1002846", "name": "Associated raw file URI", "value": "ftp://ftp.pride.ebi.ac.uk/pride/data/archive/2019/11/PXD013003/QE1_Katja_Exp8_sample7B_R.raw"}, {"accession": "MS:1002846", "name": "Associated raw file URI", "value": "ftp://ftp.pride.ebi.ac.uk/pride/data/archive/2019/11/PXD013003/QE1_Katja_Exp8_sample8B.raw"}, {"accession": "MS:1002846", "name": "Associated raw file URI", "value": "ftp://ftp.pride.ebi.ac.uk/pride/data/archive/2019/11/PXD013003/QE1_Katja_Exp8_sample8B_R.raw"}, {"accession": "MS:1002846", "name": "Associated raw file URI", "value": "ftp://ftp.pride.ebi.ac.uk/pride/data/archive/2019/11/PXD013003/QE1_Katja_Exp9_sample1A.raw"}, {"accession": "MS:1002846", "name": "Associated raw file URI", "value": "ftp://ftp.pride.ebi.ac.uk/pride/data/archive/2019/11/PXD013003/QE1_Katja_Exp9_sample1A_R.raw"}, {"accession": "MS:1002846", "name": "Associated raw file URI", "value": "ftp://ftp.pride.ebi.ac.uk/pride/data/archive/2019/11/PXD013003/QE1_Katja_Exp9_sample1B.raw"}, {"accession": "MS:1002846", "name": "Associated raw file URI", "value": "ftp://ftp.pride.ebi.ac.uk/pride/data/archive/2019/11/PXD013003/QE1_Katja_Exp9_sample1B_R.raw"}, {"accession": "MS:1002846", "name": "Associated raw file URI", "value": "ftp://ftp.pride.ebi.ac.uk/pride/data/archive/2019/11/PXD013003/QE1_Katja_Exp9_sample2A.raw"}, {"accession": "MS:1002846", "name": "Associated raw file URI", "value": "ftp://ftp.pride.ebi.ac.uk/pride/data/archive/2019/11/PXD013003/QE1_Katja_Exp9_sample2A_R.raw"}, {"accession": "MS:1002846", "name": "Associated raw file URI", "value": "ftp://ftp.pride.ebi.ac.uk/pride/data/archive/2019/11/PXD013003/QE1_Katja_Exp9_sample2B.raw"}, {"accession": "MS:1002846", "name": "Associated raw file URI", "value": "ftp://ftp.pride.ebi.ac.uk/pride/data/archive/2019/11/PXD013003/QE1_Katja_Exp9_sample2B_R.raw"}, {"accession": "MS:1002846", "name": "Associated raw file URI", "value": "ftp://ftp.pride.ebi.ac.uk/pride/data/archive/2019/11/PXD013003/QE1_Katja_Exp9_sample3A.raw"}, {"accession": "MS:1002846", "name": "Associated raw file URI", "value": "ftp://ftp.pride.ebi.ac.uk/pride/data/archive/2019/11/PXD013003/QE1_Katja_Exp9_sample3A_R.raw"}, {"accession": "MS:1002846", "name": "Associated raw file URI", "value": "ftp://ftp.pride.ebi.ac.uk/pride/data/archive/2019/11/PXD013003/QE1_Katja_Exp9_sample3B.raw"}, {"accession": "MS:1002846", "name": "Associated raw file URI", "value": "ftp://ftp.pride.ebi.ac.uk/pride/data/archive/2019/11/PXD013003/QE1_Katja_Exp9_sample3B_R.raw"}, {"accession": "MS:1002846", "name": "Associated raw file URI", "value": "ftp://ftp.pride.ebi.ac.uk/pride/data/archive/2019/11/PXD013003/QE1_Katja_Exp9_sample4A.raw"}, {"accession": "MS:1002846", "name": "Associated raw file URI", "value": "ftp://ftp.pride.ebi.ac.uk/pride/data/archive/2019/11/PXD013003/QE1_Katja_Exp9_sample4A_R.raw"}, {"accession": "MS:1002846", "name": "Associated raw file URI", "value": "ftp://ftp.pride.ebi.ac.uk/pride/data/archive/2019/11/PXD013003/QE1_Katja_Exp9_sample4B.raw"}, {"accession": "MS:1002846", "name": "Associated raw file URI", "value": "ftp://ftp.pride.ebi.ac.uk/pride/data/archive/2019/11/PXD013003/QE1_Katja_Exp9_sample4B_R.raw"}], "description": "Endothelial cells form a barrier between the components present in the blood and the underlying tissue. Essential to formation of this barrier are junctional complexes present between cells. These complexes are dynamic, tightly regulated and remodel during key physiological processes such as inflammation, angiogenesis and development to allow passage of molecules, cells and movement of endothelial cells. One such junctional protein, Jam-C, is involved in the pathology of a number of inflammatory disease states and its inhibition in vitro and in vivo results in aberrant forms of leukocyte migration, dysregulated angiogenesis and inhibition of cell migration. Intracellular trafficking has been shown to be a general means of regulating the function of junctional proteins but its role in Jam-C function is unclear. Using a combination of receptor mutagenesis, HRP and APEX-2 proximity labelling alongside light and electron microscopy, we here characterise the dynamics and route of Jam-C trafficking. Rather than trafficking with junctional proteins associated with the inflammatory process, Jam-C co-traffics with receptors associated with changes in permeability such as VE-Cadherin, NRP-1 and 2. We show that Jam-C becomes ubiquitylated by the E-3 ligase CBL and that this post translational modification controls the likelihood of its degradation in the lysosomes or its recycling back to the cell surface. Finally, we show that Jam-C trafficking is essential for some of the endothelial functions of Jam-C.", "fullDatasetLinks": [{"accession": "MS:1002852", "name": "Dataset FTP location", "value": "ftp://ftp.pride.ebi.ac.uk/pride/data/archive/2019/11/PXD013003"}, {"accession": "MS:1001930", "name": "PRIDE project URI", "value": "http://www.ebi.ac.uk/pride/archive/projects/PXD013003"}], "identifiers": [{"accession": "MS:1001919", "name": "ProteomeXchange accession number", "value": "PXD013003"}], "instruments": [{"accession": "MS:1001911", "name": "Q Exactive"}], "keywords": [{"accession": "MS:1001925", "name": "submitter keyword", "value": "Jam-C, LC-MS/MS, proteomics, intracellular trafficking, ubiquitin, endothelial cells"}], "modifications": [{"accession": "MS:1002864", "name": "No PTMs are included in the dataset"}], "publications": [{"terms": [{"accession": "MS:1002858", "name": "Dataset with its publication pending"}]}], "species": [{"terms": [{"accession": "MS:1001469", "name": "taxonomy: scientific name", "value": "Homo sapiens (Human)"}, {"accession": "MS:1001467", "name": "taxonomy: NCBI TaxID", "value": "9606"}]}], "title": "Ubiquitin mediated intracellular trafficking is required for Jam-C function"}