{"contacts": [{"terms": [{"accession": "MS:1002037", "name": "dataset submitter"}, {"accession": "MS:1000586", "name": "contact name", "value": "Ryan Lumpkin"}, {"accession": "MS:1000589", "name": "contact email", "value": "rlumpkin@ucsd.edu"}, {"accession": "MS:1000590", "name": "contact affiliation", "value": "UCSD"}]}, {"terms": [{"accession": "MS:1002332", "name": "lab head"}, {"accession": "MS:1000586", "name": "contact name", "value": "Elizabeth Komives"}, {"accession": "MS:1000589", "name": "contact email", "value": "ekomives@ucsd.edu"}, {"accession": "MS:1000590", "name": "contact affiliation", "value": "University of California, San Diego"}]}], "description": "Hydrogen Deuterium Exchange Data for the analysis of the dynamics and regulation of the ASB9 CUL-RING E3 Ubiquitin Ligase", "fullDatasetLinks": [{"accession": "MS:1002488", "name": "MassIVE dataset URI", "value": "http://massive.ucsd.edu/ProteoSAFe/dataset.jsp?task=a64baef978a84b0ba6a0ecd7d84365ae"}, {"accession": "MS:1002852", "name": "Dataset FTP location", "value": "ftp://massive.ucsd.edu/MSV000084806/"}], "identifiers": [{"accession": "MS:1002487", "name": "MassIVE dataset identifier", "value": "MSV000084806"}, {"accession": "MS:1001919", "name": "ProteomeXchange accession number", "value": "PXD017095"}, {"accession": "MS:1001921", "name": "ProteomeXchange accession number version number", "value": "1"}], "instruments": [{"accession": "MS:1001779", "name": "Synapt G2-S HDMS"}], "keywords": [{"accession": "MS:1001925", "name": "submitter keyword", "value": "Ubiquitin"}, {"accession": "MS:1001925", "name": "submitter keyword", "value": "ASB9"}, {"accession": "MS:1001925", "name": "submitter keyword", "value": "CUL5"}, {"accession": "MS:1001925", "name": "submitter keyword", "value": "RBX2"}, {"accession": "MS:1001925", "name": "submitter keyword", "value": "NEDD8"}, {"accession": "MS:1001925", "name": "submitter keyword", "value": "HDX-MS"}, {"accession": "MS:1001925", "name": "submitter keyword", "value": "HDXMS"}, {"accession": "MS:1001925", "name": "submitter keyword", "value": "HDX"}], "modifications": [{"accession": "MS:1002864", "name": "No PTMs are included in the dataset"}], "publications": [{"terms": [{"accession": "MS:1002853", "name": "Dataset with no associated published manuscript"}]}], "species": [{"terms": [{"accession": "MS:1001469", "name": "taxonomy: scientific name", "value": "Homo sapiens"}, {"accession": "MS:1001468", "name": "taxonomy: common name", "value": "human"}, {"accession": "MS:1001467", "name": "taxonomy: NCBI TaxID", "value": "9606"}]}], "title": "Stucture and Dynamics of ASB9 CUL-RING Ligase"}