{"contacts": [{"terms": [{"accession": "MS:1000586", "name": "contact name", "value": "Tuula Nyman"}, {"accession": "MS:1000589", "name": "contact email", "value": "tuula.nyman@helsinki.fi"}, {"accession": "MS:1000590", "name": "contact affiliation", "value": "Institute of Biotechnology"}, {"accession": "MS:1002037", "name": "dataset submitter"}]}, {"terms": [{"accession": "MS:1002332", "name": "lab head"}, {"accession": "MS:1000586", "name": "contact name", "value": "Tuula Nyman"}, {"accession": "MS:1000589", "name": "contact email", "value": "tuula.nyman@helsinki.fi"}, {"accession": "MS:1000590", "name": "contact affiliation", "value": "Institute of Biotechnology, University of Helsinki"}]}], "datasetFiles": [{"accession": "PRIDE:0000404", "name": "Associated raw file URI", "value": "ftp://ftp.pride.ebi.ac.uk/pride/data/archive/2014/07/PXD000670/110623 hacat_ctr1.wiff"}, {"accession": "PRIDE:0000404", "name": "Associated raw file URI", "value": "ftp://ftp.pride.ebi.ac.uk/pride/data/archive/2014/07/PXD000670/110623 hacat_ctr1.wiff.scan"}, {"accession": "PRIDE:0000404", "name": "Associated raw file URI", "value": "ftp://ftp.pride.ebi.ac.uk/pride/data/archive/2014/07/PXD000670/110623 hacat_ctr2.wiff"}, {"accession": "PRIDE:0000404", "name": "Associated raw file URI", "value": "ftp://ftp.pride.ebi.ac.uk/pride/data/archive/2014/07/PXD000670/110623 hacat_ctr2.wiff.scan"}, {"accession": "PRIDE:0000404", "name": "Associated raw file URI", "value": "ftp://ftp.pride.ebi.ac.uk/pride/data/archive/2014/07/PXD000670/110623 hacat_ctr3.wiff"}, {"accession": "PRIDE:0000404", "name": "Associated raw file URI", "value": "ftp://ftp.pride.ebi.ac.uk/pride/data/archive/2014/07/PXD000670/110623 hacat_ctr3.wiff.scan"}, {"accession": "PRIDE:0000404", "name": "Associated raw file URI", "value": "ftp://ftp.pride.ebi.ac.uk/pride/data/archive/2014/07/PXD000670/110623 hacat_ctr4.wiff"}, {"accession": "PRIDE:0000404", "name": "Associated raw file URI", "value": "ftp://ftp.pride.ebi.ac.uk/pride/data/archive/2014/07/PXD000670/110623 hacat_ctr4.wiff.scan"}, {"accession": "PRIDE:0000404", "name": "Associated raw file URI", "value": "ftp://ftp.pride.ebi.ac.uk/pride/data/archive/2014/07/PXD000670/110623 hacat_ctr5.wiff"}, {"accession": "PRIDE:0000404", "name": "Associated raw file URI", "value": "ftp://ftp.pride.ebi.ac.uk/pride/data/archive/2014/07/PXD000670/110623 hacat_ctr5.wiff.scan"}, {"accession": "PRIDE:0000404", "name": "Associated raw file URI", "value": "ftp://ftp.pride.ebi.ac.uk/pride/data/archive/2014/07/PXD000670/110623 hacat_ctr6.wiff"}, {"accession": "PRIDE:0000404", "name": "Associated raw file URI", "value": "ftp://ftp.pride.ebi.ac.uk/pride/data/archive/2014/07/PXD000670/110623 hacat_ctr6.wiff.scan"}, {"accession": "PRIDE:0000404", "name": "Associated raw file URI", "value": "ftp://ftp.pride.ebi.ac.uk/pride/data/archive/2014/07/PXD000670/110623 hacat_t1.wiff"}, {"accession": "PRIDE:0000404", "name": "Associated raw file URI", "value": "ftp://ftp.pride.ebi.ac.uk/pride/data/archive/2014/07/PXD000670/110623 hacat_t1.wiff.scan"}, {"accession": "PRIDE:0000404", "name": "Associated raw file URI", "value": "ftp://ftp.pride.ebi.ac.uk/pride/data/archive/2014/07/PXD000670/110623 hacat_t2.wiff"}, {"accession": "PRIDE:0000404", "name": "Associated raw file URI", "value": "ftp://ftp.pride.ebi.ac.uk/pride/data/archive/2014/07/PXD000670/110623 hacat_t2.wiff.scan"}, {"accession": "PRIDE:0000404", "name": "Associated raw file URI", "value": "ftp://ftp.pride.ebi.ac.uk/pride/data/archive/2014/07/PXD000670/110623 hacat_t3.wiff"}, {"accession": "PRIDE:0000404", "name": "Associated raw file URI", "value": "ftp://ftp.pride.ebi.ac.uk/pride/data/archive/2014/07/PXD000670/110623 hacat_t3.wiff.scan"}, {"accession": "PRIDE:0000404", "name": "Associated raw file URI", "value": "ftp://ftp.pride.ebi.ac.uk/pride/data/archive/2014/07/PXD000670/110623 hacat_t4.wiff"}, {"accession": "PRIDE:0000404", "name": "Associated raw file URI", "value": "ftp://ftp.pride.ebi.ac.uk/pride/data/archive/2014/07/PXD000670/110623 hacat_t4.wiff.scan"}, {"accession": "PRIDE:0000404", "name": "Associated raw file URI", "value": "ftp://ftp.pride.ebi.ac.uk/pride/data/archive/2014/07/PXD000670/110623 hacat_t5.wiff"}, {"accession": "PRIDE:0000404", "name": "Associated raw file URI", "value": "ftp://ftp.pride.ebi.ac.uk/pride/data/archive/2014/07/PXD000670/110623 hacat_t5.wiff.scan"}, {"accession": "PRIDE:0000404", "name": "Associated raw file URI", "value": "ftp://ftp.pride.ebi.ac.uk/pride/data/archive/2014/07/PXD000670/110623 hacat_t6.wiff"}, {"accession": "PRIDE:0000404", "name": "Associated raw file URI", "value": "ftp://ftp.pride.ebi.ac.uk/pride/data/archive/2014/07/PXD000670/110623 hacat_t6.wiff.scan"}, {"accession": "PRIDE:0000404", "name": "Associated raw file URI", "value": "ftp://ftp.pride.ebi.ac.uk/pride/data/archive/2014/07/PXD000670/110707 hacat_ctr1.wiff"}, {"accession": "PRIDE:0000404", "name": "Associated raw file URI", "value": "ftp://ftp.pride.ebi.ac.uk/pride/data/archive/2014/07/PXD000670/110707 hacat_ctr1.wiff.scan"}, {"accession": "PRIDE:0000404", "name": "Associated raw file URI", "value": "ftp://ftp.pride.ebi.ac.uk/pride/data/archive/2014/07/PXD000670/110707 hacat_polyIC1.wiff"}, {"accession": "PRIDE:0000404", "name": "Associated raw file URI", "value": "ftp://ftp.pride.ebi.ac.uk/pride/data/archive/2014/07/PXD000670/110707 hacat_polyIC1.wiff.scan"}, {"accession": "PRIDE:0000404", "name": "Associated raw file URI", "value": "ftp://ftp.pride.ebi.ac.uk/pride/data/archive/2014/07/PXD000670/110708 hacat_ctr2.wiff"}, {"accession": "PRIDE:0000404", "name": "Associated raw file URI", "value": "ftp://ftp.pride.ebi.ac.uk/pride/data/archive/2014/07/PXD000670/110708 hacat_ctr2.wiff.scan"}, {"accession": "PRIDE:0000404", "name": "Associated raw file URI", "value": "ftp://ftp.pride.ebi.ac.uk/pride/data/archive/2014/07/PXD000670/110708 hacat_ctr3.wiff"}, {"accession": "PRIDE:0000404", "name": "Associated raw file URI", "value": "ftp://ftp.pride.ebi.ac.uk/pride/data/archive/2014/07/PXD000670/110708 hacat_ctr3.wiff.scan"}, {"accession": "PRIDE:0000404", "name": "Associated raw file URI", "value": "ftp://ftp.pride.ebi.ac.uk/pride/data/archive/2014/07/PXD000670/110708 hacat_ctr4.wiff"}, {"accession": "PRIDE:0000404", "name": "Associated raw file URI", "value": "ftp://ftp.pride.ebi.ac.uk/pride/data/archive/2014/07/PXD000670/110708 hacat_ctr4.wiff.scan"}, {"accession": "PRIDE:0000404", "name": "Associated raw file URI", "value": "ftp://ftp.pride.ebi.ac.uk/pride/data/archive/2014/07/PXD000670/110708 hacat_ctr5.wiff"}, {"accession": "PRIDE:0000404", "name": "Associated raw file URI", "value": "ftp://ftp.pride.ebi.ac.uk/pride/data/archive/2014/07/PXD000670/110708 hacat_ctr5.wiff.scan"}, {"accession": "PRIDE:0000404", "name": "Associated raw file URI", "value": "ftp://ftp.pride.ebi.ac.uk/pride/data/archive/2014/07/PXD000670/110708 hacat_ctr6.wiff"}, {"accession": "PRIDE:0000404", "name": "Associated raw file URI", "value": "ftp://ftp.pride.ebi.ac.uk/pride/data/archive/2014/07/PXD000670/110708 hacat_ctr6.wiff.scan"}, {"accession": "PRIDE:0000404", "name": "Associated raw file URI", "value": "ftp://ftp.pride.ebi.ac.uk/pride/data/archive/2014/07/PXD000670/110708 hacat_polyIC2.wiff"}, {"accession": "PRIDE:0000404", "name": "Associated raw file URI", "value": "ftp://ftp.pride.ebi.ac.uk/pride/data/archive/2014/07/PXD000670/110708 hacat_polyIC2.wiff.scan"}, {"accession": "PRIDE:0000404", "name": "Associated raw file URI", "value": "ftp://ftp.pride.ebi.ac.uk/pride/data/archive/2014/07/PXD000670/110708 hacat_polyIC3.wiff"}, {"accession": "PRIDE:0000404", "name": "Associated raw file URI", "value": "ftp://ftp.pride.ebi.ac.uk/pride/data/archive/2014/07/PXD000670/110708 hacat_polyIC3.wiff.scan"}, {"accession": "PRIDE:0000404", "name": "Associated raw file URI", "value": "ftp://ftp.pride.ebi.ac.uk/pride/data/archive/2014/07/PXD000670/110708 hacat_polyIC4.wiff"}, {"accession": "PRIDE:0000404", "name": "Associated raw file URI", "value": "ftp://ftp.pride.ebi.ac.uk/pride/data/archive/2014/07/PXD000670/110708 hacat_polyIC4.wiff.scan"}, {"accession": "PRIDE:0000404", "name": "Associated raw file URI", "value": "ftp://ftp.pride.ebi.ac.uk/pride/data/archive/2014/07/PXD000670/110708 hacat_polyIC5.wiff"}, {"accession": "PRIDE:0000404", "name": "Associated raw file URI", "value": "ftp://ftp.pride.ebi.ac.uk/pride/data/archive/2014/07/PXD000670/110708 hacat_polyIC5.wiff.scan"}, {"accession": "PRIDE:0000404", "name": "Associated raw file URI", "value": "ftp://ftp.pride.ebi.ac.uk/pride/data/archive/2014/07/PXD000670/110708 hacat_polyIC6.wiff"}, {"accession": "PRIDE:0000404", "name": "Associated raw file URI", "value": "ftp://ftp.pride.ebi.ac.uk/pride/data/archive/2014/07/PXD000670/110708 hacat_polyIC6.wiff.scan"}, {"accession": "PRIDE:0000404", "name": "Associated raw file URI", "value": "ftp://ftp.pride.ebi.ac.uk/pride/data/archive/2014/07/PXD000670/110917 HaCaT_CTR_1a.wiff"}, {"accession": "PRIDE:0000404", "name": "Associated raw file URI", "value": "ftp://ftp.pride.ebi.ac.uk/pride/data/archive/2014/07/PXD000670/110917 HaCaT_CTR_1a.wiff.scan"}, {"accession": "PRIDE:0000404", "name": "Associated raw file URI", "value": "ftp://ftp.pride.ebi.ac.uk/pride/data/archive/2014/07/PXD000670/110917 HaCaT_CTR_2a.wiff"}, {"accession": "PRIDE:0000404", "name": "Associated raw file URI", "value": "ftp://ftp.pride.ebi.ac.uk/pride/data/archive/2014/07/PXD000670/110917 HaCaT_CTR_2a.wiff.scan"}, {"accession": "PRIDE:0000404", "name": "Associated raw file URI", "value": "ftp://ftp.pride.ebi.ac.uk/pride/data/archive/2014/07/PXD000670/110917 HaCaT_CTR_3a.wiff"}, {"accession": "PRIDE:0000404", "name": "Associated raw file URI", "value": "ftp://ftp.pride.ebi.ac.uk/pride/data/archive/2014/07/PXD000670/110917 HaCaT_CTR_3a.wiff.scan"}, {"accession": "PRIDE:0000404", "name": "Associated raw file URI", "value": "ftp://ftp.pride.ebi.ac.uk/pride/data/archive/2014/07/PXD000670/110917 HaCaT_CTR_4a.wiff"}, {"accession": "PRIDE:0000404", "name": "Associated raw file URI", "value": "ftp://ftp.pride.ebi.ac.uk/pride/data/archive/2014/07/PXD000670/110917 HaCaT_CTR_4a.wiff.scan"}, {"accession": "PRIDE:0000404", "name": "Associated raw file URI", "value": "ftp://ftp.pride.ebi.ac.uk/pride/data/archive/2014/07/PXD000670/110917 HaCaT_CTR_5a.wiff"}, {"accession": "PRIDE:0000404", "name": "Associated raw file URI", "value": "ftp://ftp.pride.ebi.ac.uk/pride/data/archive/2014/07/PXD000670/110917 HaCaT_CTR_5a.wiff.scan"}, {"accession": "PRIDE:0000404", "name": "Associated raw file URI", "value": "ftp://ftp.pride.ebi.ac.uk/pride/data/archive/2014/07/PXD000670/110917 HaCaT_CTR_6a.wiff"}, {"accession": "PRIDE:0000404", "name": "Associated raw file URI", "value": "ftp://ftp.pride.ebi.ac.uk/pride/data/archive/2014/07/PXD000670/110917 HaCaT_CTR_6a.wiff.scan"}, {"accession": "PRIDE:0000404", "name": "Associated raw file URI", "value": "ftp://ftp.pride.ebi.ac.uk/pride/data/archive/2014/07/PXD000670/110917 HaCaT_pIC_1a.wiff"}, {"accession": "PRIDE:0000404", "name": "Associated raw file URI", "value": "ftp://ftp.pride.ebi.ac.uk/pride/data/archive/2014/07/PXD000670/110917 HaCaT_pIC_1a.wiff.scan"}, {"accession": "PRIDE:0000404", "name": "Associated raw file URI", "value": "ftp://ftp.pride.ebi.ac.uk/pride/data/archive/2014/07/PXD000670/110917 HaCaT_pIC_2a.wiff"}, {"accession": "PRIDE:0000404", "name": "Associated raw file URI", "value": "ftp://ftp.pride.ebi.ac.uk/pride/data/archive/2014/07/PXD000670/110917 HaCaT_pIC_2a.wiff.scan"}, {"accession": "PRIDE:0000404", "name": "Associated raw file URI", "value": "ftp://ftp.pride.ebi.ac.uk/pride/data/archive/2014/07/PXD000670/110917 HaCaT_pIC_3a.wiff"}, {"accession": "PRIDE:0000404", "name": "Associated raw file URI", "value": "ftp://ftp.pride.ebi.ac.uk/pride/data/archive/2014/07/PXD000670/110917 HaCaT_pIC_3a.wiff.scan"}, {"accession": "PRIDE:0000404", "name": "Associated raw file URI", "value": "ftp://ftp.pride.ebi.ac.uk/pride/data/archive/2014/07/PXD000670/110917 HaCaT_pIC_4a.wiff"}, {"accession": "PRIDE:0000404", "name": "Associated raw file URI", "value": "ftp://ftp.pride.ebi.ac.uk/pride/data/archive/2014/07/PXD000670/110917 HaCaT_pIC_4a.wiff.scan"}, {"accession": "PRIDE:0000404", "name": "Associated raw file URI", "value": "ftp://ftp.pride.ebi.ac.uk/pride/data/archive/2014/07/PXD000670/110917 HaCaT_pIC_5a.wiff"}, {"accession": "PRIDE:0000404", "name": "Associated raw file URI", "value": "ftp://ftp.pride.ebi.ac.uk/pride/data/archive/2014/07/PXD000670/110917 HaCaT_pIC_5a.wiff.scan"}, {"accession": "PRIDE:0000404", "name": "Associated raw file URI", "value": "ftp://ftp.pride.ebi.ac.uk/pride/data/archive/2014/07/PXD000670/110917 HaCaT_pIC_6a.wiff"}, {"accession": "PRIDE:0000404", "name": "Associated raw file URI", "value": "ftp://ftp.pride.ebi.ac.uk/pride/data/archive/2014/07/PXD000670/110917 HaCaT_pIC_6a.wiff.scan"}, {"accession": "PRIDE:0000404", "name": "Associated raw file URI", "value": "ftp://ftp.pride.ebi.ac.uk/pride/data/archive/2014/07/PXD000670/110919 HaCaT_CTR_1b.wiff"}, {"accession": "PRIDE:0000404", "name": "Associated raw file URI", "value": "ftp://ftp.pride.ebi.ac.uk/pride/data/archive/2014/07/PXD000670/110919 HaCaT_CTR_1b.wiff.scan"}, {"accession": "PRIDE:0000404", "name": "Associated raw file URI", "value": "ftp://ftp.pride.ebi.ac.uk/pride/data/archive/2014/07/PXD000670/110919 HaCaT_CTR_2b.wiff"}, {"accession": "PRIDE:0000404", "name": "Associated raw file URI", "value": "ftp://ftp.pride.ebi.ac.uk/pride/data/archive/2014/07/PXD000670/110919 HaCaT_CTR_2b.wiff.scan"}, {"accession": "PRIDE:0000404", "name": "Associated raw file URI", "value": "ftp://ftp.pride.ebi.ac.uk/pride/data/archive/2014/07/PXD000670/110919 HaCaT_CTR_3b.wiff"}, {"accession": "PRIDE:0000404", "name": "Associated raw file URI", "value": "ftp://ftp.pride.ebi.ac.uk/pride/data/archive/2014/07/PXD000670/110919 HaCaT_CTR_3b.wiff.scan"}, {"accession": "PRIDE:0000404", "name": "Associated raw file URI", "value": "ftp://ftp.pride.ebi.ac.uk/pride/data/archive/2014/07/PXD000670/110919 HaCaT_CTR_4b.wiff"}, {"accession": "PRIDE:0000404", "name": "Associated raw file URI", "value": "ftp://ftp.pride.ebi.ac.uk/pride/data/archive/2014/07/PXD000670/110919 HaCaT_CTR_4b.wiff.scan"}, {"accession": "PRIDE:0000404", "name": "Associated raw file URI", "value": "ftp://ftp.pride.ebi.ac.uk/pride/data/archive/2014/07/PXD000670/110919 HaCaT_CTR_5b.wiff"}, {"accession": "PRIDE:0000404", "name": "Associated raw file URI", "value": "ftp://ftp.pride.ebi.ac.uk/pride/data/archive/2014/07/PXD000670/110919 HaCaT_CTR_5b.wiff.scan"}, {"accession": "PRIDE:0000404", "name": "Associated raw file URI", "value": "ftp://ftp.pride.ebi.ac.uk/pride/data/archive/2014/07/PXD000670/110919 HaCaT_CTR_6b.wiff"}, {"accession": "PRIDE:0000404", "name": "Associated raw file URI", "value": "ftp://ftp.pride.ebi.ac.uk/pride/data/archive/2014/07/PXD000670/110919 HaCaT_CTR_6b.wiff.scan"}, {"accession": "PRIDE:0000404", "name": "Associated raw file URI", "value": "ftp://ftp.pride.ebi.ac.uk/pride/data/archive/2014/07/PXD000670/110919 HaCaT_pIC_1b.wiff"}, {"accession": "PRIDE:0000404", "name": "Associated raw file URI", "value": "ftp://ftp.pride.ebi.ac.uk/pride/data/archive/2014/07/PXD000670/110919 HaCaT_pIC_1b.wiff.scan"}, {"accession": "PRIDE:0000404", "name": "Associated raw file URI", "value": "ftp://ftp.pride.ebi.ac.uk/pride/data/archive/2014/07/PXD000670/110919 HaCaT_pIC_2b.wiff"}, {"accession": "PRIDE:0000404", "name": "Associated raw file URI", "value": "ftp://ftp.pride.ebi.ac.uk/pride/data/archive/2014/07/PXD000670/110919 HaCaT_pIC_2b.wiff.scan"}, {"accession": "PRIDE:0000404", "name": "Associated raw file URI", "value": "ftp://ftp.pride.ebi.ac.uk/pride/data/archive/2014/07/PXD000670/110919 HaCaT_pIC_3b.wiff"}, {"accession": "PRIDE:0000404", "name": "Associated raw file URI", "value": "ftp://ftp.pride.ebi.ac.uk/pride/data/archive/2014/07/PXD000670/110919 HaCaT_pIC_3b.wiff.scan"}, {"accession": "PRIDE:0000404", "name": "Associated raw file URI", "value": "ftp://ftp.pride.ebi.ac.uk/pride/data/archive/2014/07/PXD000670/110919 HaCaT_pIC_4b.wiff"}, {"accession": "PRIDE:0000404", "name": "Associated raw file URI", "value": "ftp://ftp.pride.ebi.ac.uk/pride/data/archive/2014/07/PXD000670/110919 HaCaT_pIC_4b.wiff.scan"}, {"accession": "PRIDE:0000404", "name": "Associated raw file URI", "value": "ftp://ftp.pride.ebi.ac.uk/pride/data/archive/2014/07/PXD000670/110919 HaCaT_pIC_5b.wiff"}, {"accession": "PRIDE:0000404", "name": "Associated raw file URI", "value": "ftp://ftp.pride.ebi.ac.uk/pride/data/archive/2014/07/PXD000670/110919 HaCaT_pIC_5b.wiff.scan"}, {"accession": "PRIDE:0000404", "name": "Associated raw file URI", "value": "ftp://ftp.pride.ebi.ac.uk/pride/data/archive/2014/07/PXD000670/110919 HaCaT_pIC_6b.wiff"}, {"accession": "PRIDE:0000404", "name": "Associated raw file URI", "value": "ftp://ftp.pride.ebi.ac.uk/pride/data/archive/2014/07/PXD000670/110919 HaCaT_pIC_6b.wiff.scan"}, {"accession": "PRIDE:0000408", "name": "Search engine output file URI", "value": "ftp://ftp.pride.ebi.ac.uk/pride/data/archive/2014/07/PXD000670/110623 hacat_case_emphasis.xml"}, {"accession": "PRIDE:0000408", "name": "Search engine output file URI", "value": "ftp://ftp.pride.ebi.ac.uk/pride/data/archive/2014/07/PXD000670/110623 hacat_ctrl_emphasis.xml"}, {"accession": "PRIDE:0000408", "name": "Search engine output file URI", "value": "ftp://ftp.pride.ebi.ac.uk/pride/data/archive/2014/07/PXD000670/F003712.dat"}, {"accession": "PRIDE:0000408", "name": "Search engine output file URI", "value": "ftp://ftp.pride.ebi.ac.uk/pride/data/archive/2014/07/PXD000670/F003714.dat"}, {"accession": "PRIDE:0000408", "name": "Search engine output file URI", "value": "ftp://ftp.pride.ebi.ac.uk/pride/data/archive/2014/07/PXD000670/110707_hacat_case_emphasis.xml"}, {"accession": "PRIDE:0000408", "name": "Search engine output file URI", "value": "ftp://ftp.pride.ebi.ac.uk/pride/data/archive/2014/07/PXD000670/110707_hacat_ctrl_emphasis.xml"}, {"accession": "PRIDE:0000408", "name": "Search engine output file URI", "value": "ftp://ftp.pride.ebi.ac.uk/pride/data/archive/2014/07/PXD000670/F003715.dat"}, {"accession": "PRIDE:0000408", "name": "Search engine output file URI", "value": "ftp://ftp.pride.ebi.ac.uk/pride/data/archive/2014/07/PXD000670/F003717.dat"}, {"accession": "PRIDE:0000408", "name": "Search engine output file URI", "value": "ftp://ftp.pride.ebi.ac.uk/pride/data/archive/2014/07/PXD000670/110917and19_hacat_case_emphasis.xml"}, {"accession": "PRIDE:0000408", "name": "Search engine output file URI", "value": "ftp://ftp.pride.ebi.ac.uk/pride/data/archive/2014/07/PXD000670/110917and19_hacat_ctrl_emphasis.xml"}, {"accession": "PRIDE:0000408", "name": "Search engine output file URI", "value": "ftp://ftp.pride.ebi.ac.uk/pride/data/archive/2014/07/PXD000670/F003720.dat"}, {"accession": "PRIDE:0000408", "name": "Search engine output file URI", "value": "ftp://ftp.pride.ebi.ac.uk/pride/data/archive/2014/07/PXD000670/F003721.dat"}], "description": "In this study, we have used global phosphoproteomic analysis to define phosphorylation-dependent signaling events regulated during RLR stimulation in human keratinocytes. In addition, we used quantitative 14-3-3-affinity capture to identify major target molecules of 14-3-3 regulation.", "fullDatasetLinks": [{"accession": "PRIDE:0000411", "name": "Dataset FTP location", "value": "ftp://ftp.pride.ebi.ac.uk/pride/data/archive/2014/07/PXD000670"}, {"accession": "MS:1001930", "name": "PRIDE project URI", "value": "http://www.ebi.ac.uk/pride/archive/projects/PXD000670"}], "identifiers": [{"accession": "MS:1001919", "name": "ProteomeXchange accession number", "value": "PXD000670"}], "instruments": [{"accession": "MS:1000190", "name": "QSTAR"}], "keywords": [{"accession": "MS:1001925", "name": "submitter keyword", "value": "Human keratinocytes, phosphorylation, LC-MS\\MS"}, {"accession": "MS:1001926", "name": "curator keyword", "value": "Biomedical"}], "modifications": [{"accession": "MOD:00425", "name": "monohydroxylated residue"}, {"accession": "MOD:00696", "name": "phosphorylated residue"}], "publications": [{"terms": [{"accession": "MS:1000879", "name": "PubMed identifier", "value": "24997996"}, {"accession": "PRIDE:0000400", "name": "Reference", "value": "Ohman T, Soderholm S, Hintsanen P, Valimaki E, Lietzen N, MacKintosh C, Aittokallio T, Matikainen S, Nyman TA. Phosphoproteomics Combined with Quantitative 14-3-3-affinity Capture Identifies SIRT1 and RAI as Novel Regulators of Cytosolic dsRNA Recognition Pathway. Mol Cell Proteomics. 2014 Jul 5. pii: mcp.M114.038968"}]}], "species": [{"terms": [{"accession": "MS:1001469", "name": "taxonomy: scientific name", "value": "Homo sapiens (Human)"}, {"accession": "MS:1001467", "name": "taxonomy: NCBI TaxID", "value": "9606"}]}], "title": "Phosphoproteomics combined with quantitative 14-3-3-affinity capture identifies SIRT1 and RAI as new regulators of cytosolic dsRNA-induced innate immune response"}