{"contacts": [{"terms": [{"accession": "MS:1000586", "name": "contact name", "value": "Hengxu Wang"}, {"accession": "MS:1000589", "name": "contact email", "value": "1124081728@qq.com"}, {"accession": "MS:1000590", "name": "contact affiliation", "value": "College of Life Science and Agroforestry, Qiqihar University"}, {"accession": "MS:1002037", "name": "dataset submitter"}]}, {"terms": [{"accession": "MS:1002332", "name": "lab head"}, {"accession": "MS:1000586", "name": "contact name", "value": "Hengxu Wang"}, {"accession": "MS:1000589", "name": "contact email", "value": "1124081728@qq.com"}, {"accession": "MS:1000590", "name": "contact affiliation", "value": "College of Life Science and Agroforestry, Qiqihar University"}]}], "datasetFiles": [{"accession": "MS:1002846", "name": "Associated raw file URI", "value": "http://download.iprox.org/IPX0002320000/IPX0002320001/Cc20WHX_1_1.raw"}, {"accession": "MS:1002846", "name": "Associated raw file URI", "value": "http://download.iprox.org/IPX0002320000/IPX0002320001/Cc20WHX_1_2.raw"}, {"accession": "MS:1002846", "name": "Associated raw file URI", "value": "http://download.iprox.org/IPX0002320000/IPX0002320001/Cc20WHX_1_3.raw"}, {"accession": "MS:1002846", "name": "Associated raw file URI", "value": "http://download.iprox.org/IPX0002320000/IPX0002320001/Cc20WHX_2_1.raw"}, {"accession": "MS:1002846", "name": "Associated raw file URI", "value": "http://download.iprox.org/IPX0002320000/IPX0002320001/Cc20WHX_2_2.raw"}, {"accession": "MS:1002846", "name": "Associated raw file URI", "value": "http://download.iprox.org/IPX0002320000/IPX0002320001/Cc20WHX_2_3.raw"}, {"accession": "MS:1002846", "name": "Associated raw file URI", "value": "http://download.iprox.org/IPX0002320000/IPX0002320001/Cc20WHX_3_1.raw"}, {"accession": "MS:1002846", "name": "Associated raw file URI", "value": "http://download.iprox.org/IPX0002320000/IPX0002320001/Cc20WHX_3_2.raw"}, {"accession": "MS:1002846", "name": "Associated raw file URI", "value": "http://download.iprox.org/IPX0002320000/IPX0002320001/Cc20WHX_3_3.raw"}, {"accession": "MS:1002848", "name": "Result file URI", "value": "http://download.iprox.org/IPX0002320000/IPX0002320001/Cc20WHX_.pep.xml"}, {"accession": "MS:1002848", "name": "Result file URI", "value": "http://download.iprox.org/IPX0002320000/IPX0002320001/Cc20WHX_.prot.xml"}], "description": "Fusarium oxysporum f. sp. niveum induced by myriocin produced by Bacillus amyloliquefaciens LZN01", "fullDatasetLinks": [{"accession": "MS:1002837", "name": "iProX dataset URI", "value": "http://www.iprox.org/page/project.html?id=IPX0002320000"}], "identifiers": [{"accession": "MS:1001919", "name": "ProteomeXchange accession number", "value": "PXD020176"}, {"accession": "MS:1002836", "name": "iProX dataset identifier", "value": "IPX0002320000"}], "instruments": [{"accession": "MS:1002523", "name": "Q Exactive HF"}], "keywords": [{"accession": "MS:1001925", "name": "submitter keyword", "value": "myriocin"}], "modifications": [{"accession": "MS:1002864", "name": "No PTMs are included in the dataset"}], "publications": [{"terms": [{"accession": "MS:1002858", "name": "Dataset with its publication pending"}]}], "species": [{"terms": [{"accession": "MS:1001469", "name": "taxonomy: scientific name", "value": "Fusarium oxysporum f. sp. niveum"}, {"accession": "MS:1001467", "name": "taxonomy: NCBI TaxID", "value": "120297"}]}], "title": "Fusarium oxysporum f. sp. niveum induced by myriocin produced by Bacillus amyloliquefaciens LZN01"}