{"contacts": [{"terms": [{"accession": "MS:1000586", "name": "contact name", "value": "Iulia M. Lazar"}, {"accession": "MS:1000589", "name": "contact email", "value": "malazar@vt.edu"}, {"accession": "MS:1000590", "name": "contact affiliation", "value": "Virginia Tech"}, {"accession": "MS:1002037", "name": "dataset submitter"}]}, {"terms": [{"accession": "MS:1002332", "name": "lab head"}, {"accession": "MS:1000586", "name": "contact name", "value": "Iulia Lazar"}, {"accession": "MS:1000589", "name": "contact email", "value": "malazar@vt.edu"}, {"accession": "MS:1000590", "name": "contact affiliation", "value": "Virginia Tech"}]}], "datasetFiles": [{"accession": "MS:1002851", "name": "Other type file URI", "value": "ftp://ftp.pride.ebi.ac.uk/pride/data/archive/2021/10/PXD023166/checksum.txt"}, {"accession": "MS:1002849", "name": "Search engine output file URI", "value": "ftp://ftp.pride.ebi.ac.uk/pride/data/archive/2021/10/PXD023166/HMC3_SC1_1.msf"}, {"accession": "MS:1002846", "name": "Associated raw file URI", "value": "ftp://ftp.pride.ebi.ac.uk/pride/data/archive/2021/10/PXD023166/HMC3_SC1_1.raw"}, {"accession": "MS:1002849", "name": "Search engine output file URI", "value": "ftp://ftp.pride.ebi.ac.uk/pride/data/archive/2021/10/PXD023166/HMC3_SC1_2.msf"}, {"accession": "MS:1002846", "name": "Associated raw file URI", "value": "ftp://ftp.pride.ebi.ac.uk/pride/data/archive/2021/10/PXD023166/HMC3_SC1_2.raw"}, {"accession": "MS:1002849", "name": "Search engine output file URI", "value": "ftp://ftp.pride.ebi.ac.uk/pride/data/archive/2021/10/PXD023166/HMC3_SC1_3.msf"}, {"accession": "MS:1002846", "name": "Associated raw file URI", "value": "ftp://ftp.pride.ebi.ac.uk/pride/data/archive/2021/10/PXD023166/HMC3_SC1_3.raw"}, {"accession": "MS:1002849", "name": "Search engine output file URI", "value": "ftp://ftp.pride.ebi.ac.uk/pride/data/archive/2021/10/PXD023166/HMC3_SC2_1.msf"}, {"accession": "MS:1002846", "name": "Associated raw file URI", "value": "ftp://ftp.pride.ebi.ac.uk/pride/data/archive/2021/10/PXD023166/HMC3_SC2_1.raw"}, {"accession": "MS:1002849", "name": "Search engine output file URI", "value": "ftp://ftp.pride.ebi.ac.uk/pride/data/archive/2021/10/PXD023166/HMC3_SC2_2.msf"}, {"accession": "MS:1002846", "name": "Associated raw file URI", "value": "ftp://ftp.pride.ebi.ac.uk/pride/data/archive/2021/10/PXD023166/HMC3_SC2_2.raw"}, {"accession": "MS:1002849", "name": "Search engine output file URI", "value": "ftp://ftp.pride.ebi.ac.uk/pride/data/archive/2021/10/PXD023166/HMC3_SC2_3.msf"}, {"accession": "MS:1002846", "name": "Associated raw file URI", "value": "ftp://ftp.pride.ebi.ac.uk/pride/data/archive/2021/10/PXD023166/HMC3_SC2_3.raw"}, {"accession": "MS:1002849", "name": "Search engine output file URI", "value": "ftp://ftp.pride.ebi.ac.uk/pride/data/archive/2021/10/PXD023166/HMC3_SC3_1.msf"}, {"accession": "MS:1002846", "name": "Associated raw file URI", "value": "ftp://ftp.pride.ebi.ac.uk/pride/data/archive/2021/10/PXD023166/HMC3_SC3_1.raw"}, {"accession": "MS:1002849", "name": "Search engine output file URI", "value": "ftp://ftp.pride.ebi.ac.uk/pride/data/archive/2021/10/PXD023166/HMC3_SC3_2.msf"}, {"accession": "MS:1002846", "name": "Associated raw file URI", "value": "ftp://ftp.pride.ebi.ac.uk/pride/data/archive/2021/10/PXD023166/HMC3_SC3_2.raw"}, {"accession": "MS:1002849", "name": "Search engine output file URI", "value": "ftp://ftp.pride.ebi.ac.uk/pride/data/archive/2021/10/PXD023166/HMC3_SC3_3.msf"}, {"accession": "MS:1002846", "name": "Associated raw file URI", "value": "ftp://ftp.pride.ebi.ac.uk/pride/data/archive/2021/10/PXD023166/HMC3_SC3_3.raw"}, {"accession": "MS:1002849", "name": "Search engine output file URI", "value": "ftp://ftp.pride.ebi.ac.uk/pride/data/archive/2021/10/PXD023166/HMC3_SCck1_1.msf"}, {"accession": "MS:1002846", "name": "Associated raw file URI", "value": "ftp://ftp.pride.ebi.ac.uk/pride/data/archive/2021/10/PXD023166/HMC3_SCck1_1.raw"}, {"accession": "MS:1002849", "name": "Search engine output file URI", "value": "ftp://ftp.pride.ebi.ac.uk/pride/data/archive/2021/10/PXD023166/HMC3_SCck1_2.msf"}, {"accession": "MS:1002846", "name": "Associated raw file URI", "value": "ftp://ftp.pride.ebi.ac.uk/pride/data/archive/2021/10/PXD023166/HMC3_SCck1_2.raw"}, {"accession": "MS:1002849", "name": "Search engine output file URI", "value": "ftp://ftp.pride.ebi.ac.uk/pride/data/archive/2021/10/PXD023166/HMC3_SCck1_3.msf"}, {"accession": "MS:1002846", "name": "Associated raw file URI", "value": "ftp://ftp.pride.ebi.ac.uk/pride/data/archive/2021/10/PXD023166/HMC3_SCck1_3.raw"}, {"accession": "MS:1002849", "name": "Search engine output file URI", "value": "ftp://ftp.pride.ebi.ac.uk/pride/data/archive/2021/10/PXD023166/HMC3_SCck2_1.msf"}, {"accession": "MS:1002846", "name": "Associated raw file URI", "value": "ftp://ftp.pride.ebi.ac.uk/pride/data/archive/2021/10/PXD023166/HMC3_SCck2_1.raw"}, {"accession": "MS:1002849", "name": "Search engine output file URI", "value": "ftp://ftp.pride.ebi.ac.uk/pride/data/archive/2021/10/PXD023166/HMC3_SCck2_2.msf"}, {"accession": "MS:1002846", "name": "Associated raw file URI", "value": "ftp://ftp.pride.ebi.ac.uk/pride/data/archive/2021/10/PXD023166/HMC3_SCck2_2.raw"}, {"accession": "MS:1002849", "name": "Search engine output file URI", "value": "ftp://ftp.pride.ebi.ac.uk/pride/data/archive/2021/10/PXD023166/HMC3_SCck2_3.msf"}, {"accession": "MS:1002846", "name": "Associated raw file URI", "value": "ftp://ftp.pride.ebi.ac.uk/pride/data/archive/2021/10/PXD023166/HMC3_SCck2_3.raw"}, {"accession": "MS:1002849", "name": "Search engine output file URI", "value": "ftp://ftp.pride.ebi.ac.uk/pride/data/archive/2021/10/PXD023166/HMC3_SCck3_1.msf"}, {"accession": "MS:1002846", "name": "Associated raw file URI", "value": "ftp://ftp.pride.ebi.ac.uk/pride/data/archive/2021/10/PXD023166/HMC3_SCck3_1.raw"}, {"accession": "MS:1002849", "name": "Search engine output file URI", "value": "ftp://ftp.pride.ebi.ac.uk/pride/data/archive/2021/10/PXD023166/HMC3_SCck3_2.msf"}, {"accession": "MS:1002846", "name": "Associated raw file URI", "value": "ftp://ftp.pride.ebi.ac.uk/pride/data/archive/2021/10/PXD023166/HMC3_SCck3_2.raw"}, {"accession": "MS:1002849", "name": "Search engine output file URI", "value": "ftp://ftp.pride.ebi.ac.uk/pride/data/archive/2021/10/PXD023166/HMC3_SCck3_3.msf"}, {"accession": "MS:1002846", "name": "Associated raw file URI", "value": "ftp://ftp.pride.ebi.ac.uk/pride/data/archive/2021/10/PXD023166/HMC3_SCck3_3.raw"}, {"accession": "MS:1002849", "name": "Search engine output file URI", "value": "ftp://ftp.pride.ebi.ac.uk/pride/data/archive/2021/10/PXD023166/HMC3_SN1_1.msf"}, {"accession": "MS:1002846", "name": "Associated raw file URI", "value": "ftp://ftp.pride.ebi.ac.uk/pride/data/archive/2021/10/PXD023166/HMC3_SN1_1.raw"}, {"accession": "MS:1002849", "name": "Search engine output file URI", "value": "ftp://ftp.pride.ebi.ac.uk/pride/data/archive/2021/10/PXD023166/HMC3_SN1_2.msf"}, {"accession": "MS:1002846", "name": "Associated raw file URI", "value": "ftp://ftp.pride.ebi.ac.uk/pride/data/archive/2021/10/PXD023166/HMC3_SN1_2.raw"}, {"accession": "MS:1002849", "name": "Search engine output file URI", "value": "ftp://ftp.pride.ebi.ac.uk/pride/data/archive/2021/10/PXD023166/HMC3_SN1_3.msf"}, {"accession": "MS:1002846", "name": "Associated raw file URI", "value": "ftp://ftp.pride.ebi.ac.uk/pride/data/archive/2021/10/PXD023166/HMC3_SN1_3.raw"}, {"accession": "MS:1002849", "name": "Search engine output file URI", "value": "ftp://ftp.pride.ebi.ac.uk/pride/data/archive/2021/10/PXD023166/HMC3_SN2_1.msf"}, {"accession": "MS:1002846", "name": "Associated raw file URI", "value": "ftp://ftp.pride.ebi.ac.uk/pride/data/archive/2021/10/PXD023166/HMC3_SN2_1.raw"}, {"accession": "MS:1002849", "name": "Search engine output file URI", "value": "ftp://ftp.pride.ebi.ac.uk/pride/data/archive/2021/10/PXD023166/HMC3_SN2_2.msf"}, {"accession": "MS:1002846", "name": "Associated raw file URI", "value": "ftp://ftp.pride.ebi.ac.uk/pride/data/archive/2021/10/PXD023166/HMC3_SN2_2.raw"}, {"accession": "MS:1002849", "name": "Search engine output file URI", "value": "ftp://ftp.pride.ebi.ac.uk/pride/data/archive/2021/10/PXD023166/HMC3_SN2_3.msf"}, {"accession": "MS:1002846", "name": "Associated raw file URI", "value": "ftp://ftp.pride.ebi.ac.uk/pride/data/archive/2021/10/PXD023166/HMC3_SN2_3.raw"}, {"accession": "MS:1002849", "name": "Search engine output file URI", "value": "ftp://ftp.pride.ebi.ac.uk/pride/data/archive/2021/10/PXD023166/HMC3_SN3_1.msf"}, {"accession": "MS:1002846", "name": "Associated raw file URI", "value": "ftp://ftp.pride.ebi.ac.uk/pride/data/archive/2021/10/PXD023166/HMC3_SN3_1.raw"}, {"accession": "MS:1002849", "name": "Search engine output file URI", "value": "ftp://ftp.pride.ebi.ac.uk/pride/data/archive/2021/10/PXD023166/HMC3_SN3_2.msf"}, {"accession": "MS:1002846", "name": "Associated raw file URI", "value": "ftp://ftp.pride.ebi.ac.uk/pride/data/archive/2021/10/PXD023166/HMC3_SN3_2.raw"}, {"accession": "MS:1002849", "name": "Search engine output file URI", "value": "ftp://ftp.pride.ebi.ac.uk/pride/data/archive/2021/10/PXD023166/HMC3_SN3_3.msf"}, {"accession": "MS:1002846", "name": "Associated raw file URI", "value": "ftp://ftp.pride.ebi.ac.uk/pride/data/archive/2021/10/PXD023166/HMC3_SN3_3.raw"}, {"accession": "MS:1002849", "name": "Search engine output file URI", "value": "ftp://ftp.pride.ebi.ac.uk/pride/data/archive/2021/10/PXD023166/HMC3_SNck1_1.msf"}, {"accession": "MS:1002846", "name": "Associated raw file URI", "value": "ftp://ftp.pride.ebi.ac.uk/pride/data/archive/2021/10/PXD023166/HMC3_SNck1_1.raw"}, {"accession": "MS:1002849", "name": "Search engine output file URI", "value": "ftp://ftp.pride.ebi.ac.uk/pride/data/archive/2021/10/PXD023166/HMC3_SNck1_2.msf"}, {"accession": "MS:1002846", "name": "Associated raw file URI", "value": "ftp://ftp.pride.ebi.ac.uk/pride/data/archive/2021/10/PXD023166/HMC3_SNck1_2.raw"}, {"accession": "MS:1002849", "name": "Search engine output file URI", "value": "ftp://ftp.pride.ebi.ac.uk/pride/data/archive/2021/10/PXD023166/HMC3_SNck1_3.msf"}, {"accession": "MS:1002846", "name": "Associated raw file URI", "value": "ftp://ftp.pride.ebi.ac.uk/pride/data/archive/2021/10/PXD023166/HMC3_SNck1_3.raw"}, {"accession": "MS:1002849", "name": "Search engine output file URI", "value": "ftp://ftp.pride.ebi.ac.uk/pride/data/archive/2021/10/PXD023166/HMC3_SNck2_1.msf"}, {"accession": "MS:1002846", "name": "Associated raw file URI", "value": "ftp://ftp.pride.ebi.ac.uk/pride/data/archive/2021/10/PXD023166/HMC3_SNck2_1.raw"}, {"accession": "MS:1002849", "name": "Search engine output file URI", "value": "ftp://ftp.pride.ebi.ac.uk/pride/data/archive/2021/10/PXD023166/HMC3_SNck2_2.msf"}, {"accession": "MS:1002846", "name": "Associated raw file URI", "value": "ftp://ftp.pride.ebi.ac.uk/pride/data/archive/2021/10/PXD023166/HMC3_SNck2_2.raw"}, {"accession": "MS:1002849", "name": "Search engine output file URI", "value": "ftp://ftp.pride.ebi.ac.uk/pride/data/archive/2021/10/PXD023166/HMC3_SNck2_3.msf"}, {"accession": "MS:1002846", "name": "Associated raw file URI", "value": "ftp://ftp.pride.ebi.ac.uk/pride/data/archive/2021/10/PXD023166/HMC3_SNck2_3.raw"}, {"accession": "MS:1002849", "name": "Search engine output file URI", "value": "ftp://ftp.pride.ebi.ac.uk/pride/data/archive/2021/10/PXD023166/HMC3_SNck3_1.msf"}, {"accession": "MS:1002846", "name": "Associated raw file URI", "value": "ftp://ftp.pride.ebi.ac.uk/pride/data/archive/2021/10/PXD023166/HMC3_SNck3_1.raw"}, {"accession": "MS:1002849", "name": "Search engine output file URI", "value": "ftp://ftp.pride.ebi.ac.uk/pride/data/archive/2021/10/PXD023166/HMC3_SNck3_2.msf"}, {"accession": "MS:1002846", "name": "Associated raw file URI", "value": "ftp://ftp.pride.ebi.ac.uk/pride/data/archive/2021/10/PXD023166/HMC3_SNck3_2.raw"}, {"accession": "MS:1002849", "name": "Search engine output file URI", "value": "ftp://ftp.pride.ebi.ac.uk/pride/data/archive/2021/10/PXD023166/HMC3_SNck3_3.msf"}, {"accession": "MS:1002846", "name": "Associated raw file URI", "value": "ftp://ftp.pride.ebi.ac.uk/pride/data/archive/2021/10/PXD023166/HMC3_SNck3_3.raw"}], "description": "The immune functions of microglia in the brain are compromised in the presence of tumors that have the ability to \u201chijack\u201d their pro-inflammatory nature by sending out signals that promote cancer progression. To analyze the tumor-supportive microglia phenotype, human microglia cells (HMC3) were treated with anti-inflammatory cytokines in serum-enriched cell culture media, and analyzed by LC-MS/MS using an Orbitrap QE instrument.", "fullDatasetLinks": [{"accession": "MS:1002852", "name": "Dataset FTP location", "value": "ftp://ftp.pride.ebi.ac.uk/pride/data/archive/2021/10/PXD023166"}, {"accession": "MS:1001930", "name": "PRIDE project URI", "value": "http://www.ebi.ac.uk/pride/archive/projects/PXD023166"}], "identifiers": [{"accession": "MS:1001919", "name": "ProteomeXchange accession number", "value": "PXD023166"}, {"accession": "MS:1001921", "name": "ProteomeXchange accession number version number", "value": "2"}], "instruments": [{"accession": "MS:1001911", "name": "Q Exactive"}], "keywords": [{"accession": "MS:1001925", "name": "submitter keyword", "value": "HMC3, cytokines, tumor,Microglia"}], "modifications": [{"accession": "MOD:00425", "name": "monohydroxylated residue"}, {"accession": "MOD:00394", "name": "acetylated residue"}], "publications": [{"terms": [{"accession": "MS:1000879", "name": "PubMed identifier", "value": "34566949"}, {"accession": "MS:1002866", "name": "Reference", "value": "Ahuja S, Lazar IM. Systems-Level Proteomics Evaluation of Microglia Response to Tumor-Supportive Anti-Inflammatory Cytokines. Front Immunol. 2021 12:646043"}]}, {"terms": [{"accession": "MS:1001922", "name": "Digital Object Identifier (DOI)", "value": "10.3389/FIMMU.2021.646043"}]}], "species": [{"terms": [{"accession": "MS:1001469", "name": "taxonomy: scientific name", "value": "Homo sapiens (Human)"}, {"accession": "MS:1001467", "name": "taxonomy: NCBI TaxID", "value": "9606"}]}], "title": "Proteomic analysis of human microglia cells (HMC3) stimulated with anti-inflammatory cytokines using serum-enriched culture conditions"}